Workbook

Sheet Cover
B2: Space Exploration Technologies Corp. (Nasdaq: SPCX)
B3: P&L Business Case Model
B4: Actuals through Q2 2026 with quarterly forecast build through Q4 2028
B6: Prepared | C6: Claude (Anthropic) — created in claude.ai
B8: Currency / units | C8: US$ in millions unless noted
B10: Historical source | C10: SpaceX Q2 2026 earnings release (ir.spacex.com), with Q1 2026 and Q2 2025 comparatives disclosed therein
C12: SpaceX 'Reports Second Quarter 2026 Results', posted Aug 4, 2026 — https://s21.q4cdn.com/184289198/files/doc_financials/2026/q2/SpaceX-Reports-Second-Quarter-2026-Results.pdf
B14: Forecast basis | C14: Illustrative business-case projection. All forecast drivers are editable blue/yellow inputs on the Assumptions tab — this is NOT SpaceX guidance.
B16: AI compute scenario | C16: AI segment forecast is built bottom-up off a nameplate compute (GW) build-out schedule: 1.4 GW at Q2'26A, 2.2 GW at Q4'26E (consistent with management's 'more than two gigawatts' comment), 10.0 GW at Q4'27E per business-case instruction, and an illustrative continued ramp to 15.0 GW by Q4'28E.
B18: Switchable cases | C18: The Assumptions tab carries a case selector (1/2/3) governing AI capex per GW, blended revenue per GW and the marginal contract rate on new capacity. Case 1 is CoreWeave-anchored and sceptical; Case 2 reproduces management's $100B December-2026 ARR and ~1-year payback; Case 3 stresses Case 2 revenue against Nvidia's rising cost curve.
B20: Company background | C20: SpaceX completed its IPO on June 12, 2026 (Nasdaq: SPCX), raising ~$85.7B net proceeds, and issued $25B of senior notes on June 26, 2026. Q2 2026 was its first quarter reporting as a public company.
B23: Contents
B24: 1. Assumptions — forecast drivers (editable inputs), including AI compute (GW) build-out
B25: 2. KPIs — historical operating metrics (Starlink subs/ARPU, launches, AI compute)
B26: 3. Historical P&L by Segment — Space / Connectivity / AI, Q2'25, Q1'26, Q2'26, H1'25, H1'26
B27: 4. Segment Forecast Detail — quarterly build for each segment, Q3'26E-Q4'28E
B28: 5. Consolidated P&L — historical actuals + quarterly forecast through Q4 2028
B29: 6. Balance Sheet & Cash Flow — actuals at June 30, 2026 vs Dec 31, 2025
B30: 7. Dashboard — key charts
B32: Color legend:
B33: Blue = hardcoded input / actual reported figure
B34: Black = calculated formula
B35: Green = link from another sheet
B36: Yellow fill = key assumption to edit

Sheet Assumptions
A1: Forecast Assumptions
A2: Editable inputs driving Segment Forecast and Consolidated P&L. AI segment is built off a nameplate compute (GW) schedule reaching 2.2 GW at Q4'26E, 10.0 GW at Q4'27E and 15.0 GW at Q4'28E. Set the case selector below before reading any output.
A4: Driver | B4: Q3'26E | C4: Q4'26E | D4: Q1'27E | E4: Q2'27E | F4: Q3'27E | G4: Q4'27E | H4: Q1'28E | I4: Q2'28E | J4: Q3'28E | K4: Q4'28E
A5: CASE SELECTOR — type 1, 2 or 3 in the yellow cell
A6: Active case (1 / 2 / 3) | B6: 1 | C6: =CHOOSE($B$6,"CONSERVATIVE — CoreWeave-anchored","MANAGEMENT-CONSISTENT — reproduces $100B Dec-26 ARR","HIGH-CAPEX STRESS — management revenue, Nvidia cost curve") -> CONSERVATIVE — CoreWeave-anchored
A7: Case 1 CONSERVATIVE — AI economics anchored to CoreWeave's disclosed contracted rates. Produces ~$68B ARR in Dec-2026 and a ~3 year capex payback: it does NOT reproduce management's guidance, and is the sceptical benchmark.
A8: Case 2 MANAGEMENT-CONSISTENT — blended revenue per GW raised toward the level implied by the $100B ARR guidance, capex per GW raised to the ~$50B cited by Nvidia and SemiAnalysis. Reproduces both the $100B Dec-2026 ARR and a ~1 year payback on new capital.
A9: Case 3 HIGH-CAPEX STRESS — case 2 revenue, but capex per GW follows Jensen Huang's projection of $50B today rising toward $90B. Tests whether the returns survive cost inflation.
A11: CASE LIBRARY — stored inputs for each case (the active rows below pick from these)
A12: Case 1: blended revenue per GW ($mm/qtr) | B12: 2800 | C12: 2900 | D12: 2900 | E12: 2850 | F12: 2800 | G12: 2750 | H12: 2650 | I12: 2550 | J12: 2450 | K12: 2400
A13: Case 1: marginal contract rate on NEW capacity ($mm/qtr) | B13: 3200 | C13: 3300 | D13: 3300 | E13: 3200 | F13: 3150 | G13: 3100 | H13: 3000 | I13: 2900 | J13: 2800 | K13: 2700
A14: Case 1: capex per incremental GW ($mm/GW) | B14: 32000 | C14: 30000 | D14: 28000 | E14: 26500 | F14: 25000 | G14: 24000 | H14: 23000 | I14: 22000 | J14: 21500 | K14: 21000
A15: Case 2: blended revenue per GW ($mm/qtr) | B15: 6000 | C15: 6500 | D15: 6400 | E15: 6300 | F15: 6200 | G15: 6100 | H15: 5900 | I15: 5700 | J15: 5400 | K15: 5200
A16: Case 2: marginal contract rate on NEW capacity ($mm/qtr) | B16: 12000 | C16: 12000 | D16: 11800 | E16: 11500 | F16: 11200 | G16: 11000 | H16: 10500 | I16: 10000 | J16: 9500 | K16: 9000
A17: Case 2: capex per incremental GW ($mm/GW) | B17: 48000 | C17: 50000 | D17: 52000 | E17: 54000 | F17: 56000 | G17: 58000 | H17: 60000 | I17: 62000 | J17: 64000 | K17: 66000
A18: Case 3: blended revenue per GW ($mm/qtr) | B18: 6000 | C18: 6500 | D18: 6400 | E18: 6300 | F18: 6200 | G18: 6100 | H18: 5900 | I18: 5700 | J18: 5400 | K18: 5200
A19: Case 3: marginal contract rate on NEW capacity ($mm/qtr) | B19: 12000 | C19: 12000 | D19: 11800 | E19: 11500 | F19: 11200 | G19: 11000 | H19: 10500 | I19: 10000 | J19: 9500 | K19: 9000
A20: Case 3: capex per incremental GW ($mm/GW) | B20: 55000 | C20: 60000 | D20: 65000 | E20: 70000 | F20: 75000 | G20: 80000 | H20: 84000 | I20: 87000 | J20: 89000 | K20: 90000
A22: SPACE SEGMENT
A23: Revenue QoQ growth % | B23: 0.1 | C23: 0.12 | D23: 0.1 | E23: 0.09 | F23: 0.08 | G23: 0.08 | H23: 0.07 | I23: 0.07 | J23: 0.06 | K23: 0.06
A24: Cost of revenue, % of revenue | B24: 0.33 | C24: 0.32 | D24: 0.31 | E24: 0.3 | F24: 0.3 | G24: 0.29 | H24: 0.28 | I24: 0.28 | J24: 0.27 | K24: 0.27
A25: R&D, % of revenue | B25: 1 | C25: 0.9 | D25: 0.8 | E25: 0.7 | F25: 0.62 | G25: 0.55 | H25: 0.5 | I25: 0.46 | J25: 0.42 | K25: 0.39
A26: SG&A, % of revenue | B26: 0.1 | C26: 0.1 | D26: 0.09 | E26: 0.09 | F26: 0.09 | G26: 0.08 | H26: 0.08 | I26: 0.08 | J26: 0.07 | K26: 0.07
A27: Capex, % of revenue | B27: 1 | C27: 0.9 | D27: 0.75 | E27: 0.65 | F27: 0.55 | G27: 0.5 | H27: 0.45 | I27: 0.4 | J27: 0.38 | K27: 0.35
A29: CONNECTIVITY SEGMENT
A30: Net Starlink subscriber adds (millions) | B30: 1.6 | C30: 1.6 | D30: 1.5 | E30: 1.5 | F30: 1.4 | G30: 1.4 | H30: 1.3 | I30: 1.3 | J30: 1.2 | K30: 1.2
A31: Consumer ARPU ($/month) | B31: 65 | C31: 65 | D31: 64 | E31: 64 | F31: 63 | G31: 63 | H31: 62 | I31: 62 | J31: 61 | K31: 61
A32: Enterprise & Government revenue QoQ growth % | B32: 0.2 | C32: 0.18 | D32: 0.15 | E32: 0.13 | F32: 0.12 | G32: 0.11 | H32: 0.1 | I32: 0.1 | J32: 0.09 | K32: 0.09
A33: Cost of revenue, % of revenue | B33: 0.47 | C33: 0.46 | D33: 0.45 | E33: 0.44 | F33: 0.43 | G33: 0.42 | H33: 0.41 | I33: 0.41 | J33: 0.4 | K33: 0.4
A34: R&D, % of revenue | B34: 0.065 | C34: 0.062 | D34: 0.06 | E34: 0.058 | F34: 0.056 | G34: 0.055 | H34: 0.054 | I34: 0.053 | J34: 0.052 | K34: 0.051
A35: SG&A, % of revenue | B35: 0.06 | C35: 0.058 | D35: 0.056 | E35: 0.054 | F35: 0.052 | G35: 0.05 | H35: 0.049 | I35: 0.048 | J35: 0.047 | K35: 0.046
A36: Capex, % of revenue | B36: 0.3 | C36: 0.29 | D36: 0.28 | E36: 0.27 | F36: 0.26 | G36: 0.25 | H36: 0.24 | I36: 0.24 | J36: 0.23 | K36: 0.23
A38: AI SEGMENT
A39: Nameplate compute, period end (GW) | B39: 1.8 | C39: 2.2 | D39: 3 | E39: 4.5 | F39: 7 | G39: 10 | H39: 11.5 | I39: 13 | J39: 14 | K39: 15
A40: Monetizable share of compute (%) — net of internal Grok training | B40: 0.9 | C40: 0.9 | D40: 0.9 | E40: 0.9 | F40: 0.9 | G40: 0.9 | H40: 0.9 | I40: 0.9 | J40: 0.9 | K40: 0.9
A41: ACTIVE: blended revenue per GW ($mm/quarter) | B41: =CHOOSE($B$6,B12,B15,B18) -> 2800 | C41: =CHOOSE($B$6,C12,C15,C18) -> 2900 | D41: =CHOOSE($B$6,D12,D15,D18) -> 2900 | E41: =CHOOSE($B$6,E12,E15,E18) -> 2850 | F41: =CHOOSE($B$6,F12,F15,F18) -> 2800 | G41: =CHOOSE($B$6,G12,G15,G18) -> 2750 | H41: =CHOOSE($B$6,H12,H15,H18) -> 2650 | I41: =CHOOSE($B$6,I12,I15,I18) -> 2550 | ... K41: =CHOOSE($B$6,K12,K15,K18) -> 2400
A42: ACTIVE: marginal rate on new capacity ($mm/quarter) | B42: =CHOOSE($B$6,B13,B16,B19) -> 3200 | C42: =CHOOSE($B$6,C13,C16,C19) -> 3300 | D42: =CHOOSE($B$6,D13,D16,D19) -> 3300 | E42: =CHOOSE($B$6,E13,E16,E19) -> 3200 | F42: =CHOOSE($B$6,F13,F16,F19) -> 3150 | G42: =CHOOSE($B$6,G13,G16,G19) -> 3100 | H42: =CHOOSE($B$6,H13,H16,H19) -> 3000 | I42: =CHOOSE($B$6,I13,I16,I19) -> 2900 | ... K42: =CHOOSE($B$6,K13,K16,K19) -> 2700
A43: Grok subscription revenue ($mm/qtr) [ASSUMPTION - unanchored] | B43: 700 | C43: 900 | D43: 1150 | E43: 1400 | F43: 1650 | G43: 1900 | H43: 2150 | I43: 2400 | J43: 2650 | K43: 2900
A44: Cursor revenue ($mm/qtr) [ASSUMPTION - unanchored] | B44: 0 | C44: 1200 | D44: 1500 | E44: 1800 | F44: 2100 | G44: 2400 | H44: 2700 | I44: 3000 | J44: 3300 | K44: 3600
A45: Advertising revenue QoQ growth % | B45: -0.02 | C45: 0 | D45: 0.01 | E45: 0.02 | F45: 0.02 | G45: 0.02 | H45: 0.02 | I45: 0.02 | J45: 0.02 | K45: 0.02
A46: Cost of revenue, % of revenue | B46: 0.4 | C46: 0.39 | D46: 0.38 | E46: 0.37 | F46: 0.36 | G46: 0.35 | H46: 0.34 | I46: 0.34 | J46: 0.33 | K46: 0.33
A47: R&D, % of revenue | B47: 0.75 | C47: 0.65 | D47: 0.58 | E47: 0.52 | F47: 0.47 | G47: 0.43 | H47: 0.4 | I47: 0.37 | J47: 0.35 | K47: 0.33
A48: SG&A, % of revenue | B48: 0.18 | C48: 0.16 | D48: 0.15 | E48: 0.14 | F48: 0.13 | G48: 0.12 | H48: 0.11 | I48: 0.11 | J48: 0.1 | K48: 0.1
A49: ACTIVE: capex per incremental GW ($mm/GW) | B49: =CHOOSE($B$6,B14,B17,B20) -> 32000 | C49: =CHOOSE($B$6,C14,C17,C20) -> 30000 | D49: =CHOOSE($B$6,D14,D17,D20) -> 28000 | E49: =CHOOSE($B$6,E14,E17,E20) -> 26500 | F49: =CHOOSE($B$6,F14,F17,F20) -> 25000 | G49: =CHOOSE($B$6,G14,G17,G20) -> 24000 | H49: =CHOOSE($B$6,H14,H17,H20) -> 23000 | I49: =CHOOSE($B$6,I14,I17,I20) -> 22000 | ... K49: =CHOOSE($B$6,K14,K17,K20) -> 21000
A51: ORBITAL AI COMPUTE (SPECULATIVE — memo only, NOT included in Total Capex/Revenue/Net Income/Payback below)
A52: Orbital AI compute, period end (GW) — per SpaceX's own stated target | B52: 0 | C52: 0 | D52: 0 | E52: 0.1 | F52: 0.4 | G52: 1 | H52: 2 | I52: 4 | J52: 7 | K52: 10
A53: Capex per incremental orbital GW ($mm/GW) — satellites + Starship launch, no data-center build | B53: 55000 | C53: 55000 | D53: 54000 | E53: 53000 | F53: 52000 | G53: 50000 | H53: 48000 | I53: 46000 | J53: 44000 | K53: 42000
A56: D&A AND FINANCING DRIVERS (feed the 'Financing & D&A' tab)
A57: IT equipment share of capex (%) | B57: 0.7
A58: IT equipment depreciable life (quarters) | B58: 20
A59: Facility / infrastructure depreciable life (quarters) | B59: 56
A60: Quarters from capex spend to depreciation start | B60: 2
A61: Legacy non-cash addback ($mm/quarter) | B61: 3681
A62: Existing debt at Jun 30, 2026 ($mm) | B62: 39364
A63: Interest rate on existing debt (%/yr) | B63: 0.055
A64: Interest rate on NEW debt raised (%/yr) | B64: 0.065
A65: Yield on cash & marketable securities (%/yr) | B65: 0.04
A66: Minimum cash buffer ($mm) | B66: 15000
A67: Exit-month share of quarterly revenue (%) | B67: 0.38
A68: Opening cash & securities at Jun 30, 2026 ($mm) | B68: 100009
A70: BELOW-THE-LINE / CONSOLIDATED
A71: Interest expense (per quarter, $mm) | B71: -680 | C71: -700 | D71: -700 | E71: -690 | F71: -680 | G71: -670 | H71: -660 | I71: -650 | J71: -640 | K71: -630
A72: Interest income (per quarter, $mm) | B72: 700 | C72: 680 | D72: 660 | E72: 640 | F72: 630 | G72: 620 | H72: 610 | I72: 600 | J72: 590 | K72: 580
A73: Other income (expense), net (per quarter, $mm) | B73: -50 | C73: -50 | D73: -30 | E73: -20 | F73: -10 | G73: 0 | H73: 0 | I73: 0 | J73: 0 | K73: 0
A74: Effective tax adjustment (per quarter, $mm) | B74: 20 | C74: 20 | D74: 20 | E74: 20 | F74: 20 | G74: 20 | H74: 20 | I74: 20 | J74: 20 | K74: 20
A76: MARKET CAP COMPARABLES (CLOUD COMPUTING / AI INFRASTRUCTURE)
A77: Comparable company | B77: Market cap ($B) | C77: LTM revenue ($B) | D77: Mkt Cap / Revenue
A78: CoreWeave (CRWV) | B78: 44 | C78: 9.4 | D78: =B78/C78 -> 4.6808511
A79: Nebius Group (NBIS) | B79: 48.3 | C79: 0.878 | D79: =B79/C79 -> 55.01139
A80: Oracle (ORCL) | B80: 408.6 | C80: 67.35 | D80: =B80/C80 -> 6.0668151
A81: Median Mkt Cap / Revenue multiple | D81: =MEDIAN(D78:D80) -> 6.0668151
A82: Average Mkt Cap / Revenue multiple | D82: =AVERAGE(D78:D80) -> 21.919685
A84: Selected Mkt Cap / Revenue multiple (applied to SpaceX LTM revenue) | B84: =D81 -> 6.0668151
A86: PEG RATIO COMPARABLES (AI / MEGACAP TECH)
A87: Comparable company | B87: PEG ratio (5yr expected)
A88: NVIDIA (NVDA) | B88: 0.55
A89: Palantir (PLTR) | B89: 1.76
A90: Microsoft (MSFT) | B90: 1.52
A91: Median comparable PEG ratio | B91: =MEDIAN(B88:B90) -> 1.52
A92: Average comparable PEG ratio | B92: =AVERAGE(B88:B90) -> 1.2766667
A94: Selected PEG ratio (applied to SpaceX's own LTM net income growth) | B94: =B91 -> 1.52
A96: AI ASSUMPTIONS — EXTERNAL BENCHMARK CHECK (memo, not used in calculations)
A97: AI capex per GW ($B, Q3'26E -> Q4'28E) — RECALIBRATED
A98: This model (recalibrated): $32.0B -> $21.0B/GW. External comps: $20-60B/GW — Bernstein $35B, Nvidia $50-60B, Epoch AI $38B, Orennia $60B, Nebius FY26 guidance implies ~$22.5B, CoreWeave FY26 guidance implies ~$46B. Recalibrated to sit near the Bernstein/Epoch AI band and meaningfully closer to CoreWeave — deliberately below CoreWeave's own ~$46B/GW per the user's instruction.
A99: AI revenue per GW ($B/yr, Q3'26E -> Q4'28E) — RECALIBRATED
A100: This model (recalibrated): $8.0B -> $5.2B/GW/yr. External comps: SpaceX's own Q2'26A actual is ~$6.3B/GW/yr; CoreWeave's FY26 exit-ARR guidance ($18-19B) / exit active power (1.7GW) implies ~$10.9B/GW/yr. Recalibrated above SpaceX's own actual and roughly 2/3 of the way to CoreWeave's rate — deliberately below CoreWeave per the user's instruction.
A101: AI cost of revenue, % of revenue (Q3'26E -> Q4'28E) — IN LINE
A102: This model: 40% -> 33% (unchanged). External comps: CoreWeave Q1'26 gross margin 65-69%, i.e. implied COGS ~31-35% of revenue.
A103: AI R&D, % of revenue (Q3'26E -> Q4'28E) — IN LINE (if anything conservative)
A104: This model: 75% -> 33% (unchanged). External comps: SpaceX's own Q2'26A actual AI R&D ratio was 2,178/2,561 = ~85% of revenue.
A106: Sources: Bernstein/Investing.com (Nov 2025); Epoch AI 1GW TCO model (May 2026); Orennia 'What It Costs to Build a 1GW Data Center' (May 2026); Nebius FY26 capex guidance raised to $20-25B (Aug 2026); CoreWeave FY26 guidance of $30-35B capex / 1.7GW active power and $18-19B exit ARR (May-Aug 2026); CoreWeave Q1'26 10-Q gross margin. Capex/GW and revenue/GW were both recalibrated upward from the original assumptions on Aug 2026 at user request, to sit meaningfully closer to CoreWeave's real-world economics without matching them exactly. See the Segment Forecast tab's marginal payback check for the resulting effect on implied AI capex payback.
A110: Notes
A111: - Q2'26 actual results are the jump-off point. AI segment revenue = AI infrastructure revenue (revenue-generating GW x blended $/GW/quarter) + Grok subscription revenue + Cursor revenue + Advertising revenue.
... A122: - This is an illustrative business-case model, not SpaceX guidance or an analyst consensus estimate.

Sheet KPIs
A1: Operating KPIs (Actuals)
A2: Source: SpaceX Q2 2026 earnings release, segment operating & financial data tables. Forecast compute build-out is on the Assumptions tab.
A4: Metric | B4: Q2'25A | C4: Q1'26A | D4: Q2'26A
A5: CONNECTIVITY / STARLINK
A6: Starlink subscribers (millions, period end) | B6: 6 | C6: 10.3 | D6: 12
A7: Starlink ARPU ($/month) | B7: 85 | C7: 66 | D7: 66
A9: SPACE / LAUNCH
A10: Total launches (#) | B10: 46 | C10: 40 | D10: 38
A11: Customer launches (#) | B11: 9 | C11: 7 | D11: 10
A12: Internal launches (#) | B12: 37 | C12: 33 | D12: 28
A13: Customer payloads (metric tons) | B13: 88 | C13: 45 | D13: 87
A14: Internal payloads (metric tons) | B14: 563 | C14: 511 | D14: 397
A15: Mass to orbit (metric tons) | B15: 652 | C15: 556 | D15: 485
A17: AI
A18: Nameplate compute (GW) | B18: 0.4 | C18: 1 | D18: 1.4
A21: Forward compute build-out (Q3'26E-Q4'28E) is modeled on the Assumptions tab and feeds the Segment Forecast tab.

Sheet Historical P&L
A1: Historical P&L by Segment (Actuals)
A2: $ in millions. Source: SpaceX Q2 2026 earnings release (three- and six-month tables)
A4: $mm | B4: Q2'25A | C4: Q1'26A | D4: Q2'26A | E4: H1'25A | F4: H1'26A
A5: SPACE SEGMENT
A6: Launch services revenue | B6: 490 | C6: 330 | D6: 648 | E6: 1056 | F6: 978
A7: Launch & development revenue | B7: 256 | C7: 289 | D7: 314 | E7: 555 | F7: 603
A8: Space revenue | B8: =SUM(B6:B7) -> 746 | C8: =SUM(C6:C7) -> 619 | D8: =SUM(D6:D7) -> 962 | E8: =SUM(E6:E7) -> 1611 | F8: =SUM(F6:F7) -> 1581
A9: Cost of revenue | B9: 330 | C9: 281 | D9: 329 | E9: 627 | F9: 610
A10: Research & development | B10: 693 | C10: 930 | D10: 1076 | E10: 1219 | F10: 2006
A11: Selling, general & administrative | B11: 87 | C11: 70 | D11: 99 | E11: 175 | F11: 169
A12: Impairment | B12: 5 | C12: 0 | D12: 0 | E12: 29 | F12: 0
A13: Income (loss) from operations | B13: =B8-B9-B10-B11-B12 -> -369 | C13: =C8-C9-C10-C11-C12 -> -662 | D13: =D8-D9-D10-D11-D12 -> -542 | E13: =E8-E9-E10-E11-E12 -> -439 | F13: =F8-F9-F10-F11-F12 -> -1204
A14: Adjusted EBITDA | B14: -93 | C14: -351 | D14: -205 | E14: 131 | F14: -556
A15: Capex | B15: 946 | C15: 1052 | D15: 1174 | E15: 1705 | F15: 2226
A17: CONNECTIVITY SEGMENT
A18: Consumer revenue | B18: 1721 | C18: 2148 | D18: 2485 | E18: 3213 | F18: 4633
A19: Enterprise & government revenue | B19: 867 | C19: 1109 | D19: 1806 | E19: 1849 | F19: 2915
A20: Connectivity revenue | B20: =SUM(B18:B19) -> 2588 | C20: =SUM(C18:C19) -> 3257 | D20: =SUM(D18:D19) -> 4291 | E20: =SUM(E18:E19) -> 5062 | F20: =SUM(F18:F19) -> 7548
A21: Cost of revenue | B21: 1401 | C21: 1651 | D21: 2060 | E21: 2615 | F21: 3711
A22: Research & development | B22: 143 | C22: 205 | D22: 294 | E22: 266 | F22: 499
A23: Selling, general & administrative | B23: 121 | C23: 213 | D23: 281 | E23: 225 | F23: 494
A24: Income from operations | B24: =B20-B21-B22-B23 -> 923 | C24: =C20-C21-C22-C23 -> 1188 | D24: =D20-D21-D22-D23 -> 1656 | E24: =E20-E21-E22-E23 -> 1956 | F24: =F20-F21-F22-F23 -> 2844
A25: Adjusted EBITDA | B25: 1583 | C25: 2087 | D25: 2597 | E25: 3200 | F25: 4684
A26: Capex | B26: 1130 | C26: 1332 | D26: 1367 | E26: 1944 | F26: 2699
A28: AI SEGMENT
A29: Advertising revenue | B29: 426 | C29: 343 | D29: 367 | E29: 870 | F29: 710
A30: AI solutions & infrastructure revenue | B30: 311 | C30: 475 | D30: 2194 | E30: 595 | F30: 2669
A31: AI revenue | B31: =SUM(B29:B30) -> 737 | C31: =SUM(C29:C30) -> 818 | D31: =SUM(D29:D30) -> 2561 | E31: =SUM(E29:E30) -> 1465 | F31: =SUM(F29:F30) -> 3379
A32: Cost of revenue | B32: 551 | C32: 456 | D32: 1106 | E32: 1002 | F32: 1562
A33: Research & development | B33: 1122 | C33: 2379 | D33: 2178 | E33: 2030 | F33: 4557
A34: Selling, general & administrative | B34: 398 | C34: 463 | D34: 532 | E34: 699 | F34: 995
A35: Restructuring charges (credits) | B35: 190 | C35: -11 | D35: 2 | E35: 194 | F35: -9
A36: Loss from operations | B36: =B31-B32-B33-B34-B35 -> -1524 | C36: =C31-C32-C33-C34-C35 -> -2469 | D36: =D31-D32-D33-D34-D35 -> -1257 | E36: =E31-E32-E33-E34-E35 -> -2460 | F36: =F31-F32-F33-F34-F35 -> -3726
A37: Adjusted EBITDA | B37: -276 | C37: -609 | D37: 1146 | E37: -387 | F37: 537
A38: Capex | B38: 749 | C38: 7723 | D38: 15828 | E38: 3316 | F38: 23551
A40: TOTAL COMPANY (CHECK)
A41: Total revenue | B41: =B8+B20+B31 -> 4071 | C41: =C8+C20+C31 -> 4694 | D41: =D8+D20+D31 -> 7814 | E41: =E8+E20+E31 -> 8138 | F41: =F8+F20+F31 -> 12508
A42: Total income (loss) from operations | B42: =B13+B24+B36 -> -970 | C42: =C13+C24+C36 -> -1943 | D42: =D13+D24+D36 -> -143 | E42: =E13+E24+E36 -> -943 | F42: =F13+F24+F36 -> -2086

Sheet Segment Forecast
A1: Segment Forecast Detail (Illustrative Business Case)
A2: $ in millions unless noted. Q2'26A = actual jump-off quarter. Q3'26E-Q4'28E driven by Assumptions tab. AI revenue = (revenue-generating GW x blended $/GW/quarter) + Grok subscriptions + Cursor + Advertising.
A4: $mm | B4: Q2'26A | C4: Q3'26E | D4: Q4'26E | E4: Q1'27E | F4: Q2'27E | G4: Q3'27E | H4: Q4'27E | I4: Q1'28E | J4: Q2'28E | K4: Q3'28E | L4: Q4'28E
A5: SPACE SEGMENT
A6: Revenue | B6: ='Historical P&L'!D8 -> 962 | C6: =B6*(1+Assumptions!B23) -> 1058.2 | D6: =C6*(1+Assumptions!C23) -> 1185.184 | E6: =D6*(1+Assumptions!D23) -> 1303.7024 | F6: =E6*(1+Assumptions!E23) -> 1421.0356 | G6: =F6*(1+Assumptions!F23) -> 1534.7185 | H6: =G6*(1+Assumptions!G23) -> 1657.4959 | I6: =H6*(1+Assumptions!H23) -> 1773.5207 | J6: =I6*(1+Assumptions!I23) -> 1897.6671 | ... L6: =K6*(1+Assumptions!K23) -> 2132.2188
A7: QoQ growth % | C7: =Assumptions!B23 -> 0.1 | D7: =Assumptions!C23 -> 0.12 | E7: =Assumptions!D23 -> 0.1 | F7: =Assumptions!E23 -> 0.09 | G7: =Assumptions!F23 -> 0.08 | H7: =Assumptions!G23 -> 0.08 | I7: =Assumptions!H23 -> 0.07 | J7: =Assumptions!I23 -> 0.07 | ... L7: =Assumptions!K23 -> 0.06
A8: Cost of revenue | C8: =C6*Assumptions!B24 -> 349.206 | D8: =D6*Assumptions!C24 -> 379.25888 | E8: =E6*Assumptions!D24 -> 404.14774 | F8: =F6*Assumptions!E24 -> 426.31068 | G8: =G6*Assumptions!F24 -> 460.41554 | H8: =H6*Assumptions!G24 -> 480.67382 | I8: =I6*Assumptions!H24 -> 496.58578 | J8: =J6*Assumptions!I24 -> 531.34679 | ... L8: =L6*Assumptions!K24 -> 575.69906
A9: Research & development | C9: =C6*Assumptions!B25 -> 1058.2 | D9: =D6*Assumptions!C25 -> 1066.6656 | E9: =E6*Assumptions!D25 -> 1042.9619 | F9: =F6*Assumptions!E25 -> 994.72493 | G9: =G6*Assumptions!F25 -> 951.52545 | H9: =H6*Assumptions!G25 -> 911.62277 | I9: =I6*Assumptions!H25 -> 886.76033 | J9: =J6*Assumptions!I25 -> 872.92687 | ... L9: =L6*Assumptions!K25 -> 831.56532
A10: Selling, general & administrative | C10: =C6*Assumptions!B26 -> 105.82 | D10: =D6*Assumptions!C26 -> 118.5184 | E10: =E6*Assumptions!D26 -> 117.33322 | F10: =F6*Assumptions!E26 -> 127.89321 | G10: =G6*Assumptions!F26 -> 138.12466 | H10: =H6*Assumptions!G26 -> 132.59968 | I10: =I6*Assumptions!H26 -> 141.88165 | J10: =J6*Assumptions!I26 -> 151.81337 | ... L10: =L6*Assumptions!K26 -> 149.25531
A11: Income (loss) from operations | B11: ='Historical P&L'!D13 -> -542 | C11: =C6-C8-C9-C10 -> -455.026 | D11: =D6-D8-D9-D10 -> -379.25888 | E11: =E6-E8-E9-E10 -> -260.74048 | F11: =F6-F8-F9-F10 -> -127.89321 | G11: =G6-G8-G9-G10 -> -15.347185 | H11: =H6-H8-H9-H10 -> 132.59968 | I11: =I6-I8-I9-I10 -> 248.29289 | J11: =J6-J8-J9-J10 -> 341.58008 | ... L11: =L6-L8-L9-L10 -> 575.69906
A12: Capex | B12: ='Historical P&L'!D15 -> 1174 | C12: =C6*Assumptions!B27 -> 1058.2 | D12: =D6*Assumptions!C27 -> 1066.6656 | E12: =E6*Assumptions!D27 -> 977.7768 | F12: =F6*Assumptions!E27 -> 923.67315 | G12: =G6*Assumptions!F27 -> 844.09516 | H12: =H6*Assumptions!G27 -> 828.74797 | I12: =I6*Assumptions!H27 -> 798.0843 | J12: =J6*Assumptions!I27 -> 759.06684 | ... L12: =L6*Assumptions!K27 -> 746.27657
A14: CONNECTIVITY SEGMENT
A15: Starlink subscribers, period end (mm) | B15: 12 | C15: =B15+Assumptions!B30 -> 13.6 | D15: =C15+Assumptions!C30 -> 15.2 | E15: =D15+Assumptions!D30 -> 16.7 | F15: =E15+Assumptions!E30 -> 18.2 | G15: =F15+Assumptions!F30 -> 19.6 | H15: =G15+Assumptions!G30 -> 21 | I15: =H15+Assumptions!H30 -> 22.3 | J15: =I15+Assumptions!I30 -> 23.6 | ... L15: =K15+Assumptions!K30 -> 26
A16: Consumer ARPU ($/month) | B16: 66 | C16: =Assumptions!B31 -> 65 | D16: =Assumptions!C31 -> 65 | E16: =Assumptions!D31 -> 64 | F16: =Assumptions!E31 -> 64 | G16: =Assumptions!F31 -> 63 | H16: =Assumptions!G31 -> 63 | I16: =Assumptions!H31 -> 62 | J16: =Assumptions!I31 -> 62 | ... L16: =Assumptions!K31 -> 61
A17: Consumer revenue (subs x ARPU x 3 months) | B17: ='Historical P&L'!D18 -> 2485 | C17: =C15*C16*3 -> 2652 | D17: =D15*D16*3 -> 2964 | E17: =E15*E16*3 -> 3206.4 | F17: =F15*F16*3 -> 3494.4 | G17: =G15*G16*3 -> 3704.4 | H17: =H15*H16*3 -> 3969 | I17: =I15*I16*3 -> 4147.8 | J17: =J15*J16*3 -> 4389.6 | ... L17: =L15*L16*3 -> 4758
A18: Enterprise & government revenue | B18: ='Historical P&L'!D19 -> 1806 | C18: =B18*(1+Assumptions!B32) -> 2167.2 | D18: =C18*(1+Assumptions!C32) -> 2557.296 | E18: =D18*(1+Assumptions!D32) -> 2940.8904 | F18: =E18*(1+Assumptions!E32) -> 3323.2062 | G18: =F18*(1+Assumptions!F32) -> 3721.9909 | H18: =G18*(1+Assumptions!G32) -> 4131.4099 | I18: =H18*(1+Assumptions!H32) -> 4544.5509 | J18: =I18*(1+Assumptions!I32) -> 4999.006 | ... L18: =K18*(1+Assumptions!K32) -> 5939.319
A19: Connectivity revenue | B19: ='Historical P&L'!D20 -> 4291 | C19: =C17+C18 -> 4819.2 | D19: =D17+D18 -> 5521.296 | E19: =E17+E18 -> 6147.2904 | F19: =F17+F18 -> 6817.6062 | G19: =G17+G18 -> 7426.3909 | H19: =H17+H18 -> 8100.4099 | I19: =I17+I18 -> 8692.3509 | J19: =J17+J18 -> 9388.606 | ... L19: =L17+L18 -> 10697.319
A20: Cost of revenue | C20: =C19*Assumptions!B33 -> 2265.024 | D20: =D19*Assumptions!C33 -> 2539.7962 | E20: =E19*Assumptions!D33 -> 2766.2807 | F20: =F19*Assumptions!E33 -> 2999.7467 | G20: =G19*Assumptions!F33 -> 3193.3481 | H20: =H19*Assumptions!G33 -> 3402.1722 | I20: =I19*Assumptions!H33 -> 3563.8639 | J20: =J19*Assumptions!I33 -> 3849.3284 | ... L20: =L19*Assumptions!K33 -> 4278.9276
A21: Research & development | C21: =C19*Assumptions!B34 -> 313.248 | D21: =D19*Assumptions!C34 -> 342.32035 | E21: =E19*Assumptions!D34 -> 368.83742 | F21: =F19*Assumptions!E34 -> 395.42116 | G21: =G19*Assumptions!F34 -> 415.87789 | H21: =H19*Assumptions!G34 -> 445.52254 | I21: =I19*Assumptions!H34 -> 469.38695 | J21: =J19*Assumptions!I34 -> 497.59612 | ... L21: =L19*Assumptions!K34 -> 545.56327
A22: Selling, general & administrative | C22: =C19*Assumptions!B35 -> 289.152 | D22: =D19*Assumptions!C35 -> 320.23517 | E22: =E19*Assumptions!D35 -> 344.24826 | F22: =F19*Assumptions!E35 -> 368.15073 | G22: =G19*Assumptions!F35 -> 386.17233 | H22: =H19*Assumptions!G35 -> 405.02049 | I22: =I19*Assumptions!H35 -> 425.92519 | J22: =J19*Assumptions!I35 -> 450.65309 | ... L22: =L19*Assumptions!K35 -> 492.07667
A23: Income from operations | B23: ='Historical P&L'!D24 -> 1656 | C23: =C19-C20-C21-C22 -> 1951.776 | D23: =D19-D20-D21-D22 -> 2318.9443 | E23: =E19-E20-E21-E22 -> 2667.924 | F23: =F19-F20-F21-F22 -> 3054.2876 | G23: =G19-G20-G21-G22 -> 3430.9926 | H23: =H19-H20-H21-H22 -> 3847.6947 | I23: =I19-I20-I21-I22 -> 4233.1749 | J23: =J19-J20-J21-J22 -> 4591.0283 | ... L23: =L19-L20-L21-L22 -> 5380.7515
A24: Capex | B24: ='Historical P&L'!D26 -> 1367 | C24: =C19*Assumptions!B36 -> 1445.76 | D24: =D19*Assumptions!C36 -> 1601.1758 | E24: =E19*Assumptions!D36 -> 1721.2413 | F24: =F19*Assumptions!E36 -> 1840.7537 | G24: =G19*Assumptions!F36 -> 1930.8616 | H24: =H19*Assumptions!G36 -> 2025.1025 | I24: =I19*Assumptions!H36 -> 2086.1642 | J24: =J19*Assumptions!I36 -> 2253.2654 | ... L24: =L19*Assumptions!K36 -> 2460.3834
A26: AI SEGMENT
A27: Nameplate compute, period end (GW) | B27: 1.4 | C27: =Assumptions!B39 -> 1.8 | D27: =Assumptions!C39 -> 2.2 | E27: =Assumptions!D39 -> 3 | F27: =Assumptions!E39 -> 4.5 | G27: =Assumptions!F39 -> 7 | H27: =Assumptions!G39 -> 10 | I27: =Assumptions!H39 -> 11.5 | J27: =Assumptions!I39 -> 13 | ... L27: =Assumptions!K39 -> 15
A28: Monetizable share (net of internal Grok training) | B28: 1 | C28: =Assumptions!B40 -> 0.9 | D28: =Assumptions!C40 -> 0.9 | E28: =Assumptions!D40 -> 0.9 | F28: =Assumptions!E40 -> 0.9 | G28: =Assumptions!F40 -> 0.9 | H28: =Assumptions!G40 -> 0.9 | I28: =Assumptions!H40 -> 0.9 | J28: =Assumptions!I40 -> 0.9 | ... L28: =Assumptions!K40 -> 0.9
A29: Revenue-generating compute (GW) | B29: =B27*B28 -> 1.4 | C29: =C27*C28 -> 1.62 | D29: =D27*D28 -> 1.98 | E29: =E27*E28 -> 2.7 | F29: =F27*F28 -> 4.05 | G29: =G27*G28 -> 6.3 | H29: =H27*H28 -> 9 | I29: =I27*I28 -> 10.35 | ... L29: =L27*L28 -> 13.5
A30: AI infrastructure revenue per revenue-generating GW ($mm/qtr) | B30: ='Historical P&L'!D30/B27 -> 1567.1429 | C30: =Assumptions!B41 -> 2800 | D30: =Assumptions!C41 -> 2900 | E30: =Assumptions!D41 -> 2900 | F30: =Assumptions!E41 -> 2850 | G30: =Assumptions!F41 -> 2800 | H30: =Assumptions!G41 -> 2750 | I30: =Assumptions!H41 -> 2650 | J30: =Assumptions!I41 -> 2550 | ... L30: =Assumptions!K41 -> 2400
A31: AI infrastructure revenue (revenue-generating GW x $/GW/qtr) | B31: ='Historical P&L'!D30 -> 2194 | C31: =C29*C30 -> 4536 | D31: =D29*D30 -> 5742 | E31: =E29*E30 -> 7830 | F31: =F29*F30 -> 11542.5 | G31: =G29*G30 -> 17640 | H31: =H29*H30 -> 24750 | I31: =I29*I30 -> 27427.5 | J31: =J29*J30 -> 29835 | ... L31: =L29*L30 -> 32400
A32: Grok subscription revenue [ASSUMPTION — no historical anchor] | B32: 0 | C32: =Assumptions!B43 -> 700 | D32: =Assumptions!C43 -> 900 | E32: =Assumptions!D43 -> 1150 | F32: =Assumptions!E43 -> 1400 | G32: =Assumptions!F43 -> 1650 | H32: =Assumptions!G43 -> 1900 | I32: =Assumptions!H43 -> 2150 | J32: =Assumptions!I43 -> 2400 | ... L32: =Assumptions!K43 -> 2900
A33: Cursor revenue [ASSUMPTION — no historical anchor] | B33: 0 | C33: =Assumptions!B44 -> 0 | D33: =Assumptions!C44 -> 1200 | E33: =Assumptions!D44 -> 1500 | F33: =Assumptions!E44 -> 1800 | G33: =Assumptions!F44 -> 2100 | H33: =Assumptions!G44 -> 2400 | I33: =Assumptions!H44 -> 2700 | J33: =Assumptions!I44 -> 3000 | ... L33: =Assumptions!K44 -> 3600
A34: Advertising revenue | B34: ='Historical P&L'!D29 -> 367 | C34: =B34*(1+Assumptions!B45) -> 359.66 | D34: =C34*(1+Assumptions!C45) -> 359.66 | E34: =D34*(1+Assumptions!D45) -> 363.2566 | F34: =E34*(1+Assumptions!E45) -> 370.52173 | G34: =F34*(1+Assumptions!F45) -> 377.93217 | H34: =G34*(1+Assumptions!G45) -> 385.49081 | I34: =H34*(1+Assumptions!H45) -> 393.20063 | J34: =I34*(1+Assumptions!I45) -> 401.06464 | ... L34: =K34*(1+Assumptions!K45) -> 417.26765
A35: AI revenue | B35: ='Historical P&L'!D31 -> 2561 | C35: =C31+C32+C33+C34 -> 5595.66 | D35: =D31+D32+D33+D34 -> 8201.66 | E35: =E31+E32+E33+E34 -> 10843.257 | F35: =F31+F32+F33+F34 -> 15113.022 | G35: =G31+G32+G33+G34 -> 21767.932 | H35: =H31+H32+H33+H34 -> 29435.491 | I35: =I31+I32+I33+I34 -> 32670.701 | J35: =J31+J32+J33+J34 -> 35636.065 | ... L35: =L31+L32+L33+L34 -> 39317.268
A36: QoQ growth % | C36: =IFERROR(C35/B35-1,"n/a") -> 1.1849512 | D36: =IFERROR(D35/C35-1,"n/a") -> 0.46571807 | E36: =IFERROR(E35/D35-1,"n/a") -> 0.32208073 | F36: =IFERROR(F35/E35-1,"n/a") -> 0.39377147 | G36: =IFERROR(G35/F35-1,"n/a") -> 0.44034281 | H36: =IFERROR(H35/G35-1,"n/a") -> 0.35224102 | I36: =IFERROR(I35/H35-1,"n/a") -> 0.10990847 | J36: =IFERROR(J35/I35-1,"n/a") -> 0.090765241 | ... L36: =IFERROR(L35/K35-1,"n/a") -> 0.056090061
A37: Cost of revenue | C37: =C35*Assumptions!B46 -> 2238.264 | D37: =D35*Assumptions!C46 -> 3198.6474 | E37: =E35*Assumptions!D46 -> 4120.4375 | F37: =F35*Assumptions!E46 -> 5591.818 | G37: =G35*Assumptions!F46 -> 7836.4556 | H37: =H35*Assumptions!G46 -> 10302.422 | I37: =I35*Assumptions!H46 -> 11108.038 | J37: =J35*Assumptions!I46 -> 12116.262 | ... L37: =L35*Assumptions!K46 -> 12974.698
A38: Research & development | C38: =C35*Assumptions!B47 -> 4196.745 | D38: =D35*Assumptions!C47 -> 5331.079 | E38: =E35*Assumptions!D47 -> 6289.0888 | F38: =F35*Assumptions!E47 -> 7858.7713 | G38: =G35*Assumptions!F47 -> 10230.928 | H38: =H35*Assumptions!G47 -> 12657.261 | I38: =I35*Assumptions!H47 -> 13068.28 | J38: =J35*Assumptions!I47 -> 13185.344 | ... L38: =L35*Assumptions!K47 -> 12974.698
A39: Selling, general & administrative | C39: =C35*Assumptions!B48 -> 1007.2188 | D39: =D35*Assumptions!C48 -> 1312.2656 | E39: =E35*Assumptions!D48 -> 1626.4885 | F39: =F35*Assumptions!E48 -> 2115.823 | G39: =G35*Assumptions!F48 -> 2829.8312 | H39: =H35*Assumptions!G48 -> 3532.2589 | I39: =I35*Assumptions!H48 -> 3593.7771 | J39: =J35*Assumptions!I48 -> 3919.9671 | ... L39: =L35*Assumptions!K48 -> 3931.7268
A40: Income (loss) from operations | B40: ='Historical P&L'!D36 -> -1257 | C40: =C35-C37-C38-C39 -> -1846.5678 | D40: =D35-D37-D38-D39 -> -1640.332 | E40: =E35-E37-E38-E39 -> -1192.7582 | F40: =F35-F37-F38-F39 -> -453.39065 | G40: =G35-G37-G38-G39 -> 870.71729 | H40: =H35-H37-H38-H39 -> 2943.5491 | I40: =I35-I37-I38-I39 -> 4900.6051 | J40: =J35-J37-J38-J39 -> 6414.4916 | ... L40: =L35-L37-L38-L39 -> 9436.1442
A41: Incremental GW added in quarter | B41: 0.4 | C41: =C27-B27 -> 0.4 | D41: =D27-C27 -> 0.4 | E41: =E27-D27 -> 0.8 | F41: =F27-E27 -> 1.5 | G41: =G27-F27 -> 2.5 | H41: =H27-G27 -> 3 | I41: =I27-H27 -> 1.5 | J41: =J27-I27 -> 1.5 | ... L41: =L27-K27 -> 1
A42: Capex per incremental GW ($mm/GW) | B42: ='Historical P&L'!D38/B41 -> 39570 | C42: =Assumptions!B49 -> 32000 | D42: =Assumptions!C49 -> 30000 | E42: =Assumptions!D49 -> 28000 | F42: =Assumptions!E49 -> 26500 | G42: =Assumptions!F49 -> 25000 | H42: =Assumptions!G49 -> 24000 | I42: =Assumptions!H49 -> 23000 | J42: =Assumptions!I49 -> 22000 | ... L42: =Assumptions!K49 -> 21000
A43: Marginal contract rate on new capacity ($mm/GW/qtr) | C43: =Assumptions!B42 -> 3200 | D43: =Assumptions!C42 -> 3300 | E43: =Assumptions!D42 -> 3300 | F43: =Assumptions!E42 -> 3200 | G43: =Assumptions!F42 -> 3150 | H43: =Assumptions!G42 -> 3100 | I43: =Assumptions!H42 -> 3000 | J43: =Assumptions!I42 -> 2900 | ... L43: =Assumptions!K42 -> 2700
A44: AI Capex (compute + data center + cooling) | B44: ='Historical P&L'!D38 -> 15828 | C44: =C41*C42 -> 12800 | D44: =D41*D42 -> 12000 | E44: =E41*E42 -> 22400 | F44: =F41*F42 -> 39750 | G44: =G41*G42 -> 62500 | H44: =H41*H42 -> 72000 | I44: =I41*I42 -> 34500 | J44: =J41*J42 -> 33000 | ... L44: =L41*L42 -> 21000
A45: Payback on MANAGEMENT basis (capex/GW / marginal rate, no lag) | C45: =C42/(C43*4) -> 2.5 | D45: =D42/(D43*4) -> 2.2727273 | E45: =E42/(E43*4) -> 2.1212121 | F45: =F42/(F43*4) -> 2.0703125 | G45: =G42/(G43*4) -> 1.984127 | H45: =H42/(H43*4) -> 1.9354839 | I45: =I42/(I43*4) -> 1.9166667 | J45: =J42/(J43*4) -> 1.8965517 | ... L45: =L42/(L43*4) -> 1.9444444
A46: Meets the <1-year claim? | C46: =IF(C45<1,"Yes","No") -> No | D46: =IF(D45<1,"Yes","No") -> No | E46: =IF(E45<1,"Yes","No") -> No | F46: =IF(F45<1,"Yes","No") -> No | G46: =IF(G45<1,"Yes","No") -> No | H46: =IF(H45<1,"Yes","No") -> No | I46: =IF(I45<1,"Yes","No") -> No | J46: =IF(J45<1,"Yes","No") -> No | ... L46: =IF(L45<1,"Yes","No") -> No
A47: Marginal capex payback (years) — 6mo lag, vintage rate, monetizable GW only | B47: =0.5+B42/(D30*D28*4) -> 4.2902299 | C47: =0.5+C42/(E30*E28*4) -> 3.5651341 | D47: =0.5+D42/(F30*F28*4) -> 3.4239766 | E47: =0.5+E42/(G30*G28*4) -> 3.2777778 | F47: =0.5+F42/(H30*H28*4) -> 3.1767677 | G47: =0.5+G42/(I30*I28*4) -> 3.1205451 | H47: =0.5+H42/(J30*J28*4) -> 3.1143791 | I47: =0.5+I42/(K30*K28*4) -> 3.1077098 | J47: =0.5+J42/(L30*L28*4) -> 3.0462963 | K47: ="n/a" -> n/a | L47: ="n/a" -> n/a
A48: Meets SpaceX's <1-year AI compute payback guidance? | B48: =IF(B47="n/a","n/a",IF(B47<=1,"Yes","No")) -> No | C48: =IF(C47="n/a","n/a",IF(C47<=1,"Yes","No")) -> No | D48: =IF(D47="n/a","n/a",IF(D47<=1,"Yes","No")) -> No | E48: =IF(E47="n/a","n/a",IF(E47<=1,"Yes","No")) -> No | F48: =IF(F47="n/a","n/a",IF(F47<=1,"Yes","No")) -> No | G48: =IF(G47="n/a","n/a",IF(G47<=1,"Yes","No")) -> No | H48: =IF(H47="n/a","n/a",IF(H47<=1,"Yes","No")) -> No | I48: =IF(I47="n/a","n/a",IF(I47<=1,"Yes","No")) -> No | ... L48: =IF(L47="n/a","n/a",IF(L47<=1,"Yes","No")) -> n/a
A49: Two payback measures are shown. The MANAGEMENT basis divides capex per GW by the annualised marginal contract rate that new capacity earns, with no build lag and no internal-use haircut — this is the closest reconstruction of what the CFO's 'less than one-year payback' most likely means, and Case 2 reproduces it. The measure below is deliberately stricter. Marginal basis: capex committed in quarter X is assumed to come online and start earning revenue only in quarter X+2 (6-month build/ramp lag — no revenue during that window), monetized at the $/GW rate the model assumes will prevail in quarter X+2 (not a blended, whole-portfolio average). Capex is incurred on ALL GW built, but only the monetizable share earns revenue, so the internal Grok training allocation lengthens payback proportionally. Last 2 forecast columns show "n/a" because quarter X+2 falls beyond this model's Q4'28E horizon.
A51: ORBITAL AI COMPUTE (SPECULATIVE MEMO — additive to terrestrial GW above; excluded from Total Capex/Revenue/Net Income/Payback)
A52: Orbital AI compute, period end (GW) | B52: 0 | C52: =Assumptions!B52 -> 0 | D52: =Assumptions!C52 -> 0 | E52: =Assumptions!D52 -> 0 | F52: =Assumptions!E52 -> 0.1 | G52: =Assumptions!F52 -> 0.4 | H52: =Assumptions!G52 -> 1 | I52: =Assumptions!H52 -> 2 | J52: =Assumptions!I52 -> 4 | ... L52: =Assumptions!K52 -> 10
A53: Incremental orbital GW added in quarter | B53: 0 | C53: =C52-B52 -> 0 | D53: =D52-C52 -> 0 | E53: =E52-D52 -> 0 | F53: =F52-E52 -> 0.1 | G53: =G52-F52 -> 0.3 | H53: =H52-G52 -> 0.6 | I53: =I52-H52 -> 1 | J53: =J52-I52 -> 2 | ... L53: =L52-K52 -> 3
A54: Capex per incremental orbital GW ($mm/GW) | C54: =Assumptions!B53 -> 55000 | D54: =Assumptions!C53 -> 55000 | E54: =Assumptions!D53 -> 54000 | F54: =Assumptions!E53 -> 53000 | G54: =Assumptions!F53 -> 52000 | H54: =Assumptions!G53 -> 50000 | I54: =Assumptions!H53 -> 48000 | J54: =Assumptions!I53 -> 46000 | ... L54: =Assumptions!K53 -> 42000
A55: Orbital AI capex (satellites + Starship launch) — MEMO, not in Total Capex | B55: 0 | C55: =C53*C54 -> 0 | D55: =D53*D54 -> 0 | E55: =E53*E54 -> 0 | F55: =F53*F54 -> 5300 | G55: =G53*G54 -> 15600 | H55: =H53*H54 -> 30000 | I55: =I53*I54 -> 48000 | J55: =J53*J54 -> 92000 | ... L55: =L53*L54 -> 126000
A56: Orbital AI revenue — MEMO, n/a (no operational satellites, no disclosed monetization plan) | B56: ="n/a" -> n/a | C56: ="n/a" -> n/a | D56: ="n/a" -> n/a | E56: ="n/a" -> n/a | F56: ="n/a" -> n/a | G56: ="n/a" -> n/a | H56: ="n/a" -> n/a | I56: ="n/a" -> n/a | ... L56: ="n/a" -> n/a
A57: SpaceX's own stated target: 1 GW of orbital AI compute by end of 2027, 'order of magnitude' annual scaling thereafter (per its S-1 and June 2026 AI1/Gigasat disclosures) — Musk cautioned to 'take this with a grain of salt.' Capex/GW is anchored to the ~$55B total Gigasat program cost against its 1GW target, since there is no comparable-company or operating data for satellite-based AI compute. No revenue line is forecast: no orbital satellites have launched, and SpaceX has not disclosed a monetization plan or timeline. This entire block is excluded from every other calculation in this model (Total Capex, Total AI Revenue, Consolidated P&L, Net Income, Implied Market Cap, AI capex payback) so the core forecast stays anchored to actual reported results — treat these rows as a separate 'blue sky' scenario, not part of the base case.
A59: TOTAL COMPANY
A60: Total revenue | B60: =B6+B19+B35 -> 7814 | C60: =C6+C19+C35 -> 11473.06 | D60: =D6+D19+D35 -> 14908.14 | E60: =E6+E19+E35 -> 18294.249 | F60: =F6+F19+F35 -> 23351.663 | G60: =G6+G19+G35 -> 30729.042 | H60: =H6+H19+H35 -> 39193.397 | I60: =I6+I19+I35 -> 43136.572 | ... L60: =L6+L19+L35 -> 52146.805
A61: Total income (loss) from operations | B61: =B11+B23+B40 -> -143 | C61: =C11+C23+C40 -> -349.8178 | D61: =D11+D23+D40 -> 299.35344 | E61: =E11+E23+E40 -> 1214.4253 | F61: =F11+F23+F40 -> 2473.0037 | G61: =G11+G23+G40 -> 4286.3627 | H61: =H11+H23+H40 -> 6923.8435 | I61: =I11+I23+I40 -> 9382.0729 | ... L61: =L11+L23+L40 -> 15392.595
A62: Operating margin % | B62: =B61/B60 -> -0.018300486 | C62: =C61/C60 -> -0.030490366 | D62: =D61/D60 -> 0.020079865 | E62: =E61/E60 -> 0.0663829 | F62: =F61/F60 -> 0.10590268 | G62: =G61/G60 -> 0.13948898 | H62: =H61/H60 -> 0.17665842 | I62: =I61/I60 -> 0.21749695 | ... L62: =L61/L60 -> 0.2951781
A63: Total Capex | B63: =B12+B24+B44 -> 18369 | C63: =C12+C24+C44 -> 15303.96 | D63: =D12+D24+D44 -> 14667.841 | E63: =E12+E24+E44 -> 25099.018 | F63: =F12+F24+F44 -> 42514.427 | G63: =G12+G24+G44 -> 65274.957 | H63: =H12+H24+H44 -> 74853.85 | I63: =I12+I24+I44 -> 37384.249 | ... L63: =L12+L24+L44 -> 24206.66
A64: of which: AI compute & cooling capex | B64: =B44/B63 -> 0.86166912 | C64: =C44/C63 -> 0.83638483 | D64: =D44/D63 -> 0.81811629 | E64: =E44/E63 -> 0.89246519 | F64: =F44/F63 -> 0.93497674 | G64: =G44/G63 -> 0.95748819 | H64: =H44/H63 -> 0.96187437 | I64: =I44/I63 -> 0.92284856 | ... L64: =L44/L63 -> 0.86752985

Sheet Consolidated P&L
A1: Consolidated P&L — Actuals & Forecast
A2: $ in millions. Historical columns link to Historical P&L; forecast columns link to Segment Forecast + Assumptions, through Q4 2028
A4: $mm | B4: Q2'25A | C4: Q1'26A | D4: Q2'26A | E4: Q3'26E | F4: Q4'26E | G4: Q1'27E | H4: Q2'27E | I4: Q3'27E | J4: Q4'27E | K4: Q1'28E | L4: Q2'28E | M4: Q3'28E | N4: Q4'28E
A5: REVENUE BY SEGMENT
A6: Space | B6: ='Historical P&L'!B8 -> 746 | C6: ='Historical P&L'!C8 -> 619 | D6: ='Segment Forecast'!B6 -> 962 | E6: ='Segment Forecast'!C6 -> 1058.2 | F6: ='Segment Forecast'!D6 -> 1185.184 | G6: ='Segment Forecast'!E6 -> 1303.7024 | H6: ='Segment Forecast'!F6 -> 1421.0356 | I6: ='Segment Forecast'!G6 -> 1534.7185 | J6: ='Segment Forecast'!H6 -> 1657.4959 | K6: ='Segment Forecast'!I6 -> 1773.5207 | ... N6: ='Segment Forecast'!L6 -> 2132.2188
A7: Connectivity | B7: ='Historical P&L'!B20 -> 2588 | C7: ='Historical P&L'!C20 -> 3257 | D7: ='Segment Forecast'!B19 -> 4291 | E7: ='Segment Forecast'!C19 -> 4819.2 | F7: ='Segment Forecast'!D19 -> 5521.296 | G7: ='Segment Forecast'!E19 -> 6147.2904 | H7: ='Segment Forecast'!F19 -> 6817.6062 | I7: ='Segment Forecast'!G19 -> 7426.3909 | J7: ='Segment Forecast'!H19 -> 8100.4099 | K7: ='Segment Forecast'!I19 -> 8692.3509 | ... N7: ='Segment Forecast'!L19 -> 10697.319
A8: AI | B8: ='Historical P&L'!B31 -> 737 | C8: ='Historical P&L'!C31 -> 818 | D8: ='Segment Forecast'!B35 -> 2561 | E8: ='Segment Forecast'!C35 -> 5595.66 | F8: ='Segment Forecast'!D35 -> 8201.66 | G8: ='Segment Forecast'!E35 -> 10843.257 | H8: ='Segment Forecast'!F35 -> 15113.022 | I8: ='Segment Forecast'!G35 -> 21767.932 | J8: ='Segment Forecast'!H35 -> 29435.491 | K8: ='Segment Forecast'!I35 -> 32670.701 | ... N8: ='Segment Forecast'!L35 -> 39317.268
A9: Total revenue | B9: =SUM(B6:B8) -> 4071 | C9: =SUM(C6:C8) -> 4694 | D9: =SUM(D6:D8) -> 7814 | E9: =SUM(E6:E8) -> 11473.06 | F9: =SUM(F6:F8) -> 14908.14 | G9: =SUM(G6:G8) -> 18294.249 | H9: =SUM(H6:H8) -> 23351.663 | I9: =SUM(I6:I8) -> 30729.042 | ... N9: =SUM(N6:N8) -> 52146.805
A10: YoY growth % | F10: =IFERROR(F9/B9-1,"n/a") -> 2.6620339 | G10: =IFERROR(G9/C9-1,"n/a") -> 2.8973689 | H10: =IFERROR(H9/D9-1,"n/a") -> 1.9884391 | I10: =IFERROR(I9/E9-1,"n/a") -> 1.6783649 | J10: =IFERROR(J9/F9-1,"n/a") -> 1.6289931 | K10: =IFERROR(K9/G9-1,"n/a") -> 1.3579307 | L10: =IFERROR(L9/H9-1,"n/a") -> 1.0093788 | M10: =IFERROR(M9/I9-1,"n/a") -> 0.60200016 | N10: =IFERROR(N9/J9-1,"n/a") -> 0.33049977
A12: REVENUE RUN-RATE — MANAGEMENT'S ARR BASIS (exit month x 12)
A13: Exit-month revenue (final month of quarter) | E13: =E9*Assumptions!$B$67 -> 4359.7628 | F13: =F9*Assumptions!$B$67 -> 5665.0932 | G13: =G9*Assumptions!$B$67 -> 6951.8148 | H13: =H9*Assumptions!$B$67 -> 8873.6321 | I13: =I9*Assumptions!$B$67 -> 11677.036 | J13: =J9*Assumptions!$B$67 -> 14893.491 | K13: =K9*Assumptions!$B$67 -> 16391.897 | L13: =L9*Assumptions!$B$67 -> 17830.488 | ... N13: =N9*Assumptions!$B$67 -> 19815.786
A14: ARR (exit month x 12) | E14: =E13*12 -> 52317.154 | F14: =F13*12 -> 67981.118 | G14: =G13*12 -> 83421.777 | H14: =H13*12 -> 106483.59 | I14: =I13*12 -> 140124.43 | J14: =J13*12 -> 178721.89 | K14: =K13*12 -> 196702.77 | L14: =L13*12 -> 213965.86 | ... N14: =N13*12 -> 237789.43
A15: Gap to management's $100B December 2026 guidance | F15: =F14-100000 -> -32018.882
A16: Management measures ARR as expected December revenue annualised, not the quarter multiplied by four, and states it inclusive of Cursor. This block puts the model on that same basis so the comparison is like-for-like. The exit-month share is an input on the Assumptions tab.
A18: COSTS & EXPENSES
A19: Cost of revenue | B19: =2282 -> 2282 | C19: ='Historical P&L'!C9+'Historical P&L'!C21+'Historical P&L'!C32 -> 2388 | D19: ='Historical P&L'!D9+'Historical P&L'!D21+'Historical P&L'!D32 -> 3495 | E19: ='Segment Forecast'!C8+'Segment Forecast'!C20+'Segment Forecast'!C37 -> 4852.494 | F19: ='Segment Forecast'!D8+'Segment Forecast'!D20+'Segment Forecast'!D37 -> 6117.7024 | G19: ='Segment Forecast'!E8+'Segment Forecast'!E20+'Segment Forecast'!E37 -> 7290.8659 | H19: ='Segment Forecast'!F8+'Segment Forecast'!F20+'Segment Forecast'!F37 -> 9017.8754 | I19: ='Segment Forecast'!G8+'Segment Forecast'!G20+'Segment Forecast'!G37 -> 11490.219 | J19: ='Segment Forecast'!H8+'Segment Forecast'!H20+'Segment Forecast'!H37 -> 14185.268 | K19: ='Segment Forecast'!I8+'Segment Forecast'!I20+'Segment Forecast'!I37 -> 15168.488 | L19: ='Segment Forecast'!J8+'Segment Forecast'!J20+'Segment Forecast'!J37 -> 16496.937 | ... N19: ='Segment Forecast'!L8+'Segment Forecast'!L20+'Segment Forecast'!L37 -> 17829.325
A20: Research & development | B20: =1958 -> 1958 | C20: ='Historical P&L'!C10+'Historical P&L'!C22+'Historical P&L'!C33 -> 3514 | D20: ='Historical P&L'!D10+'Historical P&L'!D22+'Historical P&L'!D33 -> 3548 | E20: ='Segment Forecast'!C9+'Segment Forecast'!C21+'Segment Forecast'!C38 -> 5568.193 | F20: ='Segment Forecast'!D9+'Segment Forecast'!D21+'Segment Forecast'!D38 -> 6740.065 | G20: ='Segment Forecast'!E9+'Segment Forecast'!E21+'Segment Forecast'!E38 -> 7700.8882 | H20: ='Segment Forecast'!F9+'Segment Forecast'!F21+'Segment Forecast'!F38 -> 9248.9174 | I20: ='Segment Forecast'!G9+'Segment Forecast'!G21+'Segment Forecast'!G38 -> 11598.331 | J20: ='Segment Forecast'!H9+'Segment Forecast'!H21+'Segment Forecast'!H38 -> 14014.406 | K20: ='Segment Forecast'!I9+'Segment Forecast'!I21+'Segment Forecast'!I38 -> 14424.428 | L20: ='Segment Forecast'!J9+'Segment Forecast'!J21+'Segment Forecast'!J38 -> 14555.867 | ... N20: ='Segment Forecast'!L9+'Segment Forecast'!L21+'Segment Forecast'!L38 -> 14351.827
A21: Selling, general & administrative | B21: =606 -> 606 | C21: ='Historical P&L'!C11+'Historical P&L'!C23+'Historical P&L'!C34 -> 746 | D21: ='Historical P&L'!D11+'Historical P&L'!D23+'Historical P&L'!D34 -> 912 | E21: ='Segment Forecast'!C10+'Segment Forecast'!C22+'Segment Forecast'!C39 -> 1402.1908 | F21: ='Segment Forecast'!D10+'Segment Forecast'!D22+'Segment Forecast'!D39 -> 1751.0192 | G21: ='Segment Forecast'!E10+'Segment Forecast'!E22+'Segment Forecast'!E39 -> 2088.07 | H21: ='Segment Forecast'!F10+'Segment Forecast'!F22+'Segment Forecast'!F39 -> 2611.867 | I21: ='Segment Forecast'!G10+'Segment Forecast'!G22+'Segment Forecast'!G39 -> 3354.1282 | J21: ='Segment Forecast'!H10+'Segment Forecast'!H22+'Segment Forecast'!H39 -> 4069.8791 | K21: ='Segment Forecast'!I10+'Segment Forecast'!I22+'Segment Forecast'!I39 -> 4161.5839 | L21: ='Segment Forecast'!J10+'Segment Forecast'!J22+'Segment Forecast'!J39 -> 4522.4336 | ... N21: ='Segment Forecast'!L10+'Segment Forecast'!L22+'Segment Forecast'!L39 -> 4573.0588
A22: Restructuring charges (credits) | B22: 190 | C22: -11 | D22: 2 | E22: 0 | F22: 0 | G22: 0 | H22: 0 | I22: 0 | J22: 0 | K22: 0 | L22: 0 | M22: 0 | N22: 0
A23: Impairment | B23: 5 | C23: 0 | D23: 0 | E23: 0 | F23: 0 | G23: 0 | H23: 0 | I23: 0 | J23: 0 | K23: 0 | L23: 0 | M23: 0 | N23: 0
A24: Total costs and expenses (excl. new-capex D&A) | B24: =SUM(B19:B23) -> 5041 | C24: =SUM(C19:C23) -> 6637 | D24: =SUM(D19:D23) -> 7957 | E24: =SUM(E19:E23) -> 11822.878 | F24: =SUM(F19:F23) -> 14608.787 | G24: =SUM(G19:G23) -> 17079.824 | H24: =SUM(H19:H23) -> 20878.66 | I24: =SUM(I19:I23) -> 26442.679 | ... N24: =SUM(N19:N23) -> 36754.211
A25: Operating income (loss) before new-capex D&A | B25: =B9-B24 -> -970 | C25: =C9-C24 -> -1943 | D25: =D9-D24 -> -143 | E25: =E9-E24 -> -349.8178 | F25: =F9-F24 -> 299.35344 | G25: =G9-G24 -> 1214.4253 | H25: =H9-H24 -> 2473.0037 | I25: =I9-I24 -> 4286.3627 | ... N25: =N9-N24 -> 15392.595
A26: Depreciation on new forecast-period capex | B26: 0 | C26: 0 | D26: 0 | E26: ='Financing & D&A'!B8 -> 0 | F26: ='Financing & D&A'!C8 -> 0 | G26: ='Financing & D&A'!D8 -> 617.6241 | H26: ='Financing & D&A'!E8 -> 1209.5763 | I26: ='Financing & D&A'!F8 -> 2222.5009 | J26: ='Financing & D&A'!G8 -> 3938.2617 | K26: ='Financing & D&A'!H8 -> 6572.5725 | L26: ='Financing & D&A'!I8 -> 9593.46 | ... N26: ='Financing & D&A'!K8 -> 12555.536
A27: Historical columns show zero because depreciation on assets already in service at Q2'26 is embedded in the reported cost lines above (and in the cost ratios used to forecast them). Only depreciation on NEW capex spent during the forecast is added here, to avoid double-counting.
A28: Total costs and expenses | B28: =B24+B26 -> 5041 | C28: =C24+C26 -> 6637 | D28: =D24+D26 -> 7957 | E28: =E24+E26 -> 11822.878 | F28: =F24+F26 -> 14608.787 | G28: =G24+G26 -> 17697.448 | H28: =H24+H26 -> 22088.236 | I28: =I24+I26 -> 28665.18 | ... N28: =N24+N26 -> 49309.747
A29: Income (loss) from operations | B29: =B9-B28 -> -970 | C29: =C9-C28 -> -1943 | D29: =D9-D28 -> -143 | E29: =E9-E28 -> -349.8178 | F29: =F9-F28 -> 299.35344 | G29: =G9-G28 -> 596.80123 | H29: =H9-H28 -> 1263.4274 | I29: =I9-I28 -> 2063.8618 | ... N29: =N9-N28 -> 2837.0584
A30: Operating margin % | B30: =B29/B9 -> -0.2382707 | C30: =C29/C9 -> -0.41393268 | D30: =D29/D9 -> -0.018300486 | E30: =E29/E9 -> -0.030490366 | F30: =F29/F9 -> 0.020079865 | G30: =G29/G9 -> 0.03262234 | H30: =H29/H9 -> 0.054104386 | I30: =I29/I9 -> 0.067163233 | ... N30: =N29/N9 -> 0.05440522
A32: BELOW THE LINE
A33: Interest expense | B33: -411 | C33: -664 | D33: -629 | E33: ='Financing & D&A'!B14 -> -541.255 | F33: ='Financing & D&A'!C14 -> -541.255 | G33: ='Financing & D&A'!D14 -> -541.255 | H33: ='Financing & D&A'!E14 -> -541.255 | I33: ='Financing & D&A'!F14 -> -541.255 | J33: ='Financing & D&A'!G14 -> -1367.7959 | K33: ='Financing & D&A'!H14 -> -2431.9565 | L33: ='Financing & D&A'!I14 -> -2864.5824 | ... N33: ='Financing & D&A'!K14 -> -3417.7727
A34: Interest income | B34: 98 | C34: 213 | D34: 340 | E34: ='Financing & D&A'!B12 -> 1000.09 | F34: ='Financing & D&A'!C12 -> 884.75057 | G34: ='Financing & D&A'!D12 -> 781.11065 | H34: ='Financing & D&A'!E12 -> 581.27328 | I34: ='Financing & D&A'!F12 -> 217.86923 | J34: ='Financing & D&A'!G12 -> 150 | K34: ='Financing & D&A'!H12 -> 150 | L34: ='Financing & D&A'!I12 -> 150 | ... N34: ='Financing & D&A'!K12 -> 150
A35: Other income (expense), net | B35: 413 | C35: -1876 | D35: -86 | E35: =Assumptions!B73 -> -50 | F35: =Assumptions!C73 -> -50 | G35: =Assumptions!D73 -> -30 | H35: =Assumptions!E73 -> -20 | I35: =Assumptions!F73 -> -10 | J35: =Assumptions!G73 -> 0 | K35: =Assumptions!H73 -> 0 | L35: =Assumptions!I73 -> 0 | ... N35: =Assumptions!K73 -> 0
A36: Loss before income taxes | B36: =B29+B33+B34+B35 -> -870 | C36: =C29+C33+C34+C35 -> -4270 | D36: =D29+D33+D34+D35 -> -518 | E36: =E29+E33+E34+E35 -> 59.0172 | F36: =F29+F33+F34+F35 -> 592.84901 | G36: =G29+G33+G34+G35 -> 806.65688 | H36: =H29+H33+H34+H35 -> 1283.4457 | I36: =I29+I33+I34+I35 -> 1730.476 | ... N36: =N29+N33+N34+N35 -> -430.71423
A37: Provision for income taxes | B37: 138 | C37: 6 | D37: 23 | E37: =Assumptions!B74 -> 20 | F37: =Assumptions!C74 -> 20 | G37: =Assumptions!D74 -> 20 | H37: =Assumptions!E74 -> 20 | I37: =Assumptions!F74 -> 20 | J37: =Assumptions!G74 -> 20 | K37: =Assumptions!H74 -> 20 | L37: =Assumptions!I74 -> 20 | ... N37: =Assumptions!K74 -> 20
A38: Net income (loss) | B38: =B36-B37 -> -1008 | C38: =C36-C37 -> -4276 | D38: =D36-D37 -> -541 | E38: =E36-E37 -> 39.0172 | F38: =F36-F37 -> 572.84901 | G38: =G36-G37 -> 786.65688 | H38: =H36-H37 -> 1263.4457 | I38: =I36-I37 -> 1710.476 | ... N38: =N36-N37 -> -450.71423
A39: Net margin % | B39: =B38/B9 -> -0.24760501 | C39: =C38/C9 -> -0.91095015 | D39: =D38/D9 -> -0.069234707 | E39: =E38/E9 -> 0.0034007667 | F39: =F38/F9 -> 0.03842525 | G39: =G38/G9 -> 0.043000227 | H39: =H38/H9 -> 0.054105169 | I39: =I38/I9 -> 0.055663174 | ... N39: =N38/N9 -> -0.0086431802
A41: ADJUSTED EBITDA (memo)
A42: Adjusted EBITDA | B42: 1214 | C42: 1127 | D42: 3538 | E42: =E29+E26+Assumptions!$B$61 -> 3331.1822 | F42: =F29+F26+Assumptions!$B$61 -> 3980.3534 | G42: =G29+G26+Assumptions!$B$61 -> 4895.4253 | H42: =H29+H26+Assumptions!$B$61 -> 6154.0037 | I42: =I29+I26+Assumptions!$B$61 -> 7967.3627 | J42: =J29+J26+Assumptions!$B$61 -> 10604.843 | K42: =K29+K26+Assumptions!$B$61 -> 13063.073 | L42: =L29+L26+Assumptions!$B$61 -> 15028.1 | ... N42: =N29+N26+Assumptions!$B$61 -> 19073.595
A43: Forecast Adjusted EBITDA = operating income + new-capex depreciation + the legacy non-cash addback held flat from Q2'26A. Now computable because depreciation is an explicit line.
A45: IMPLIED MARKET CAP (memo — cloud computing comps)
A46: LTM revenue (trailing 4 quarters) | F46: =SUM(C9:F9) -> 38889.2 | G46: =SUM(D9:G9) -> 52489.449 | H46: =SUM(E9:H9) -> 68027.113 | I46: =SUM(F9:I9) -> 87283.094 | J46: =SUM(G9:J9) -> 111568.35 | K46: =SUM(H9:K9) -> 136410.67 | L46: =SUM(I9:L9) -> 159981.35 | M46: =SUM(J9:M9) -> 178480.24 | N46: =SUM(K9:N9) -> 191433.64
A47: Selected Mkt Cap / Revenue multiple (from Assumptions) | F47: =Assumptions!$B$84 -> 6.0668151 | G47: =Assumptions!$B$84 -> 6.0668151 | H47: =Assumptions!$B$84 -> 6.0668151 | I47: =Assumptions!$B$84 -> 6.0668151 | J47: =Assumptions!$B$84 -> 6.0668151 | K47: =Assumptions!$B$84 -> 6.0668151 | L47: =Assumptions!$B$84 -> 6.0668151 | M47: =Assumptions!$B$84 -> 6.0668151 | N47: =Assumptions!$B$84 -> 6.0668151
A48: Implied market cap ($B) | F48: =F46*F47/1000 -> 235.93359 | G48: =G46*G47/1000 -> 318.44379 | H48: =H46*H47/1000 -> 412.70792 | I48: =I46*I47/1000 -> 529.5304 | J48: =J46*J47/1000 -> 676.86456 | K48: =K46*K47/1000 -> 827.57834 | L48: =L46*L47/1000 -> 970.57727 | M48: =M46*M47/1000 -> 1082.8066 | N48: =N46*N47/1000 -> 1161.3925
A49: LTM net income (loss) | F49: =SUM(C38:F38) -> -4205.1338 | G49: =SUM(D38:G38) -> 857.52309 | H49: =SUM(E38:H38) -> 2661.9688 | I49: =SUM(F38:I38) -> 4333.4276 | J49: =SUM(G38:J38) -> 5508.3644 | K49: =SUM(H38:K38) -> 5229.2514 | L49: =SUM(I38:L38) -> 2984.8633 | M49: =SUM(J38:M38) -> 729.00374 | N49: =SUM(K38:N38) -> -1469.4963
A50: Implied P/E ratio | F50: =IF(F49<=0,"n/m",F48*1000/F49) -> n/m | G50: =IF(G49<=0,"n/m",G48*1000/G49) -> 371.35302 | H50: =IF(H49<=0,"n/m",H48*1000/H49) -> 155.0386 | I50: =IF(I49<=0,"n/m",I48*1000/I49) -> 122.19667 | J50: =IF(J49<=0,"n/m",J48*1000/J49) -> 122.87941 | K50: =IF(K49<=0,"n/m",K48*1000/K49) -> 158.25943 | L50: =IF(L49<=0,"n/m",L48*1000/L49) -> 325.1664 | M50: =IF(M49<=0,"n/m",M48*1000/M49) -> 1485.3238 | N50: =IF(N49<=0,"n/m",N48*1000/N49) -> n/m
A51: LTM net income YoY growth % (memo) | J51: =IF(OR(F49<=0,J49<=0),"n/m",J49/F49-1) -> n/m | K51: =IF(OR(G49<=0,K49<=0),"n/m",K49/G49-1) -> 5.0980882 | L51: =IF(OR(H49<=0,L49<=0),"n/m",L49/H49-1) -> 0.12129915 | M51: =IF(OR(I49<=0,M49<=0),"n/m",M49/I49-1) -> -0.83177203 | N51: =IF(OR(J49<=0,N49<=0),"n/m",N49/J49-1) -> n/m
A52: Implied PEG ratio | J52: =IF(OR(J50="n/m",J51="n/m",J51<=0),"n/m",J50/(J51*100)) -> n/m | K52: =IF(OR(K50="n/m",K51="n/m",K51<=0),"n/m",K50/(K51*100)) -> 0.31042898 | L52: =IF(OR(L50="n/m",L51="n/m",L51<=0),"n/m",L50/(L51*100)) -> 26.806982 | M52: =IF(OR(M50="n/m",M51="n/m",M51<=0),"n/m",M50/(M51*100)) -> n/m | N52: =IF(OR(N50="n/m",N51="n/m",N51<=0),"n/m",N50/(N51*100)) -> n/m
A53: P/E = implied market cap / LTM net income; shows "n/m" while LTM net income is <=0. PEG = P/E / LTM net income YoY growth (%, growth expressed as a whole number, e.g. 25 for 25%) — the standard convention, though PEG is designed for steady-state earnings growth and is a rough gauge here given SpaceX's early, lumpy path to profitability.
A54: Implied P/E from peer PEG benchmark (memo) | J54: =IF(J51="n/m","n/m",Assumptions!$B$94*J51*100) -> n/m | K54: =IF(K51="n/m","n/m",Assumptions!$B$94*K51*100) -> 774.9094 | L54: =IF(L51="n/m","n/m",Assumptions!$B$94*L51*100) -> 18.43747 | M54: =IF(M51="n/m","n/m",Assumptions!$B$94*M51*100) -> -126.42935 | N54: =IF(N51="n/m","n/m",Assumptions!$B$94*N51*100) -> n/m
A55: Implied market cap ($B, PEG-based) | J55: =IF(J54="n/m","n/m",J54*J49/1000) -> n/m | K55: =IF(K54="n/m","n/m",K54*K49/1000) -> 4052.1961 | L55: =IF(L54="n/m","n/m",L54*L49/1000) -> 55.033329 | M55: =IF(M54="n/m","n/m",M54*M49/1000) -> -92.167467 | N55: =IF(N54="n/m","n/m",N54*N49/1000) -> n/m
A56: PEG-based market cap = (selected peer PEG x SpaceX's own LTM net income YoY growth %) x LTM net income. Peer PEG benchmark set: NVIDIA, Palantir, Microsoft (median, editable on Assumptions). Only computable once a prior-year LTM net income base exists (Q4'27E onward) — same constraint as the PEG ratio above. CAUTION: this method is extremely sensitive to SpaceX's near-term earnings growth rate, which is elevated (100-750%+ YoY) because net income is compounding off a very small base shortly after turning profitable — peer PEGs assume much more moderate steady-state growth (10-40%/yr). The result is implausibly large implied values below; this line is shown for completeness against the PEG methodology the user requested, not as a reliable valuation. The revenue-multiple market cap above is the more defensible estimate at this stage.
A57: Note: comparable-multiple valuation only; ignores SpaceX's actual IPO-day market cap, dual-class share structure, and founder-control premium/discount. Not a price target.
A59: CAPITAL EXPENDITURES (memo)
A60: Space capex | B60: ='Historical P&L'!B15 -> 946 | C60: ='Historical P&L'!C15 -> 1052 | D60: ='Segment Forecast'!B12 -> 1174 | E60: ='Segment Forecast'!C12 -> 1058.2 | F60: ='Segment Forecast'!D12 -> 1066.6656 | G60: ='Segment Forecast'!E12 -> 977.7768 | H60: ='Segment Forecast'!F12 -> 923.67315 | I60: ='Segment Forecast'!G12 -> 844.09516 | J60: ='Segment Forecast'!H12 -> 828.74797 | K60: ='Segment Forecast'!I12 -> 798.0843 | ... N60: ='Segment Forecast'!L12 -> 746.27657
A61: Connectivity capex | B61: ='Historical P&L'!B26 -> 1130 | C61: ='Historical P&L'!C26 -> 1332 | D61: ='Segment Forecast'!B24 -> 1367 | E61: ='Segment Forecast'!C24 -> 1445.76 | F61: ='Segment Forecast'!D24 -> 1601.1758 | G61: ='Segment Forecast'!E24 -> 1721.2413 | H61: ='Segment Forecast'!F24 -> 1840.7537 | I61: ='Segment Forecast'!G24 -> 1930.8616 | J61: ='Segment Forecast'!H24 -> 2025.1025 | K61: ='Segment Forecast'!I24 -> 2086.1642 | ... N61: ='Segment Forecast'!L24 -> 2460.3834
A62: AI capex (compute + data center + cooling) | B62: ='Historical P&L'!B38 -> 749 | C62: ='Historical P&L'!C38 -> 7723 | D62: ='Segment Forecast'!B44 -> 15828 | E62: ='Segment Forecast'!C44 -> 12800 | F62: ='Segment Forecast'!D44 -> 12000 | G62: ='Segment Forecast'!E44 -> 22400 | H62: ='Segment Forecast'!F44 -> 39750 | I62: ='Segment Forecast'!G44 -> 62500 | J62: ='Segment Forecast'!H44 -> 72000 | K62: ='Segment Forecast'!I44 -> 34500 | ... N62: ='Segment Forecast'!L44 -> 21000
A63: Total capex | B63: =SUM(B60:B62) -> 2825 | C63: =SUM(C60:C62) -> 10107 | D63: =SUM(D60:D62) -> 18369 | E63: =SUM(E60:E62) -> 15303.96 | F63: =SUM(F60:F62) -> 14667.841 | G63: =SUM(G60:G62) -> 25099.018 | H63: =SUM(H60:H62) -> 42514.427 | I63: =SUM(I60:I62) -> 65274.957 | ... N63: =SUM(N60:N62) -> 24206.66
A64: of which: AI compute & cooling % | B64: =B62/B63 -> 0.26513274 | C64: =C62/C63 -> 0.76412387 | D64: =D62/D63 -> 0.86166912 | E64: =E62/E63 -> 0.83638483 | F64: =F62/F63 -> 0.81811629 | G64: =G62/G63 -> 0.89246519 | H64: =H62/H63 -> 0.93497674 | I64: =I62/I63 -> 0.95748819 | ... N64: =N62/N63 -> 0.86752985
A65: Cumulative AI capex, Q3'26E onward | E65: =E62 -> 12800 | F65: =E65+F62 -> 24800 | G65: =F65+G62 -> 47200 | H65: =G65+H62 -> 86950 | I65: =H65+I62 -> 149450 | J65: =I65+J62 -> 221450 | K65: =J65+K62 -> 255950 | L65: =K65+L62 -> 288950 | M65: =L65+M62 -> 310450 | N65: =M65+N62 -> 331450
A66: AI capex per incremental GW is a blended compute + data-center + cooling + power build cost, editable on Assumptions. Space/Connectivity capex are modeled as % of segment revenue.

Sheet Financing & D&A
A1: Depreciation & Financing Schedule
A2: $ in millions. Forecast quarters only. Drives the depreciation and interest lines on the Consolidated P&L.
A4: $mm | B4: Q3'26E | C4: Q4'26E | D4: Q1'27E | E4: Q2'27E | F4: Q3'27E | G4: Q4'27E | H4: Q1'28E | I4: Q2'28E | J4: Q3'28E | K4: Q4'28E
A5: DEPRECIATION ON NEW FORECAST-PERIOD CAPEX
A6: Total capex in quarter (vintage) | B6: ='Consolidated P&L'!E63 -> 15303.96 | C6: ='Consolidated P&L'!F63 -> 14667.841 | D6: ='Consolidated P&L'!G63 -> 25099.018 | E6: ='Consolidated P&L'!H63 -> 42514.427 | F6: ='Consolidated P&L'!I63 -> 65274.957 | G6: ='Consolidated P&L'!J63 -> 74853.85 | H6: ='Consolidated P&L'!K63 -> 37384.249 | I6: ='Consolidated P&L'!L63 -> 36012.332 | ... K6: ='Consolidated P&L'!N63 -> 24206.66
A7: Quarterly depreciation from this vintage | B7: =B6*(Assumptions!$B$57/Assumptions!$B$58+(1-Assumptions!$B$57)/Assumptions!$B$59) -> 617.6241 | C7: =C6*(Assumptions!$B$57/Assumptions!$B$58+(1-Assumptions!$B$57)/Assumptions!$B$59) -> 591.95217 | D7: =D6*(Assumptions!$B$57/Assumptions!$B$58+(1-Assumptions!$B$57)/Assumptions!$B$59) -> 1012.9247 | E7: =E6*(Assumptions!$B$57/Assumptions!$B$58+(1-Assumptions!$B$57)/Assumptions!$B$59) -> 1715.7608 | F7: =F6*(Assumptions!$B$57/Assumptions!$B$58+(1-Assumptions!$B$57)/Assumptions!$B$59) -> 2634.3108 | G7: =G6*(Assumptions!$B$57/Assumptions!$B$58+(1-Assumptions!$B$57)/Assumptions!$B$59) -> 3020.8875 | H7: =H6*(Assumptions!$B$57/Assumptions!$B$58+(1-Assumptions!$B$57)/Assumptions!$B$59) -> 1508.7215 | I7: =I6*(Assumptions!$B$57/Assumptions!$B$58+(1-Assumptions!$B$57)/Assumptions!$B$59) -> 1453.3548 | ... K7: =K6*(Assumptions!$B$57/Assumptions!$B$58+(1-Assumptions!$B$57)/Assumptions!$B$59) -> 976.91163
A8: Depreciation on new capex (cumulative, in service) | B8: =0 -> 0 | C8: =0 -> 0 | D8: =C8+B7 -> 617.6241 | E8: =D8+C7 -> 1209.5763 | F8: =E8+D7 -> 2222.5009 | G8: =F8+E7 -> 3938.2617 | H8: =G8+F7 -> 6572.5725 | I8: =H8+G7 -> 9593.46 | J8: =I8+H7 -> 11102.181 | K8: =J8+I7 -> 12555.536
A10: CASH, DEBT & INTEREST
A11: Opening cash & securities | B11: =Assumptions!$B$68 -> 100009 | C11: =B22 -> 88475.057 | D11: =C22 -> 78111.065 | E11: =D22 -> 58127.328 | F11: =E22 -> 21786.923 | G11: =F22 -> 15000 | H11: =G22 -> 15000 | I11: =H22 -> 15000 | J11: =I22 -> 15000 | K11: =J22 -> 15000
A12: Interest income (opening cash x yield) | B12: =B11*Assumptions!$B$65/4 -> 1000.09 | C12: =C11*Assumptions!$B$65/4 -> 884.75057 | D12: =D11*Assumptions!$B$65/4 -> 781.11065 | E12: =E11*Assumptions!$B$65/4 -> 581.27328 | F12: =F11*Assumptions!$B$65/4 -> 217.86923 | G12: =G11*Assumptions!$B$65/4 -> 150 | H12: =H11*Assumptions!$B$65/4 -> 150 | I12: =I11*Assumptions!$B$65/4 -> 150 | ... K12: =K11*Assumptions!$B$65/4 -> 150
A13: Opening NEW debt balance | B13: =0 -> 0 | C13: =B23 -> 0 | D13: =C23 -> 0 | E13: =D23 -> 0 | F13: =E23 -> 0 | G13: =F23 -> 50864.057 | H13: =G23 -> 116350.86 | I13: =H23 -> 142973.99 | J13: =I23 -> 166692.81 | K13: =J23 -> 177016.47
A14: Interest expense (existing + new debt) | B14: =-(Assumptions!$B$62*Assumptions!$B$63/4+B13*Assumptions!$B$64/4) -> -541.255 | C14: =-(Assumptions!$B$62*Assumptions!$B$63/4+C13*Assumptions!$B$64/4) -> -541.255 | D14: =-(Assumptions!$B$62*Assumptions!$B$63/4+D13*Assumptions!$B$64/4) -> -541.255 | E14: =-(Assumptions!$B$62*Assumptions!$B$63/4+E13*Assumptions!$B$64/4) -> -541.255 | F14: =-(Assumptions!$B$62*Assumptions!$B$63/4+F13*Assumptions!$B$64/4) -> -541.255 | G14: =-(Assumptions!$B$62*Assumptions!$B$63/4+G13*Assumptions!$B$64/4) -> -1367.7959 | H14: =-(Assumptions!$B$62*Assumptions!$B$63/4+H13*Assumptions!$B$64/4) -> -2431.9565 | I14: =-(Assumptions!$B$62*Assumptions!$B$63/4+I13*Assumptions!$B$64/4) -> -2864.5824 | ... K14: =-(Assumptions!$B$62*Assumptions!$B$63/4+K13*Assumptions!$B$64/4) -> -3417.7727
A15: Operating income before new-capex D&A | B15: ='Consolidated P&L'!E25 -> -349.8178 | C15: ='Consolidated P&L'!F25 -> 299.35344 | D15: ='Consolidated P&L'!G25 -> 1214.4253 | E15: ='Consolidated P&L'!H25 -> 2473.0037 | F15: ='Consolidated P&L'!I25 -> 4286.3627 | G15: ='Consolidated P&L'!J25 -> 6923.8435 | H15: ='Consolidated P&L'!K25 -> 9382.0729 | I15: ='Consolidated P&L'!L25 -> 11347.1 | ... K15: ='Consolidated P&L'!N25 -> 15392.595
A16: Add back: legacy non-cash charges | B16: =Assumptions!$B$61 -> 3681 | C16: =Assumptions!$B$61 -> 3681 | D16: =Assumptions!$B$61 -> 3681 | E16: =Assumptions!$B$61 -> 3681 | F16: =Assumptions!$B$61 -> 3681 | G16: =Assumptions!$B$61 -> 3681 | H16: =Assumptions!$B$61 -> 3681 | I16: =Assumptions!$B$61 -> 3681 | ... K16: =Assumptions!$B$61 -> 3681
A17: Less: cash taxes | B17: =-Assumptions!B74 -> -20 | C17: =-Assumptions!C74 -> -20 | D17: =-Assumptions!D74 -> -20 | E17: =-Assumptions!E74 -> -20 | F17: =-Assumptions!F74 -> -20 | G17: =-Assumptions!G74 -> -20 | H17: =-Assumptions!H74 -> -20 | I17: =-Assumptions!I74 -> -20 | ... K17: =-Assumptions!K74 -> -20
A18: Operating cash flow (proxy) | B18: =B15+B16+B17+B12+B14 -> 3770.0172 | C18: =C15+C16+C17+C12+C14 -> 4303.849 | D18: =D15+D16+D17+D12+D14 -> 5115.281 | E18: =E15+E16+E17+E12+E14 -> 6174.022 | F18: =F15+F16+F17+F12+F14 -> 7623.9769 | G18: =G15+G16+G17+G12+G14 -> 9367.0475 | H18: =H15+H16+H17+H12+H14 -> 10761.116 | I18: =I15+I16+I17+I12+I14 -> 12293.518 | ... K18: =K15+K16+K17+K12+K14 -> 15785.822
A19: Less: capex | B19: =-B6 -> -15303.96 | C19: =-C6 -> -14667.841 | D19: =-D6 -> -25099.018 | E19: =-E6 -> -42514.427 | F19: =-F6 -> -65274.957 | G19: =-G6 -> -74853.85 | H19: =-H6 -> -37384.249 | I19: =-I6 -> -36012.332 | ... K19: =-K6 -> -24206.66
A20: Cash before financing | B20: =B11+B18+B19 -> 88475.057 | C20: =C11+C18+C19 -> 78111.065 | D20: =D11+D18+D19 -> 58127.328 | E20: =E11+E18+E19 -> 21786.923 | F20: =F11+F18+F19 -> -35864.057 | G20: =G11+G18+G19 -> -50486.803 | H20: =H11+H18+H19 -> -11623.132 | I20: =I11+I18+I19 -> -8718.8146 | ... K20: =K11+K18+K19 -> 6579.1621
A21: New debt drawn to hold minimum cash | B21: =MAX(0,Assumptions!$B$66-B20) -> 0 | C21: =MAX(0,Assumptions!$B$66-C20) -> 0 | D21: =MAX(0,Assumptions!$B$66-D20) -> 0 | E21: =MAX(0,Assumptions!$B$66-E20) -> 0 | F21: =MAX(0,Assumptions!$B$66-F20) -> 50864.057 | G21: =MAX(0,Assumptions!$B$66-G20) -> 65486.803 | H21: =MAX(0,Assumptions!$B$66-H20) -> 26623.132 | I21: =MAX(0,Assumptions!$B$66-I20) -> 23718.815 | ... K21: =MAX(0,Assumptions!$B$66-K20) -> 8420.8379
A22: Closing cash & securities | B22: =B20+B21 -> 88475.057 | C22: =C20+C21 -> 78111.065 | D22: =D20+D21 -> 58127.328 | E22: =E20+E21 -> 21786.923 | F22: =F20+F21 -> 15000 | G22: =G20+G21 -> 15000 | H22: =H20+H21 -> 15000 | I22: =I20+I21 -> 15000 | ... K22: =K20+K21 -> 15000
A23: Closing NEW debt balance | B23: =B13+B21 -> 0 | C23: =C13+C21 -> 0 | D23: =D13+D21 -> 0 | E23: =E13+E21 -> 0 | F23: =F13+F21 -> 50864.057 | G23: =G13+G21 -> 116350.86 | H23: =H13+H21 -> 142973.99 | I23: =I13+I21 -> 166692.81 | ... K23: =K13+K21 -> 185437.31
A24: Total debt outstanding (existing + new) | B24: =Assumptions!$B$62+B23 -> 39364 | C24: =Assumptions!$B$62+C23 -> 39364 | D24: =Assumptions!$B$62+D23 -> 39364 | E24: =Assumptions!$B$62+E23 -> 39364 | F24: =Assumptions!$B$62+F23 -> 90228.057 | G24: =Assumptions!$B$62+G23 -> 155714.86 | H24: =Assumptions!$B$62+H23 -> 182337.99 | I24: =Assumptions!$B$62+I23 -> 206056.81 | ... K24: =Assumptions!$B$62+K23 -> 224801.31
A25: Memo: cumulative new debt raised | B25: =B23 -> 0 | C25: =C23 -> 0 | D25: =D23 -> 0 | E25: =E23 -> 0 | F25: =F23 -> 50864.057 | G25: =G23 -> 116350.86 | H25: =H23 -> 142973.99 | I25: =I23 -> 166692.81 | ... K25: =K23 -> 185437.31
A27: QUARTERLY FREE CASH FLOW
A28: EBITDA (op income before new-capex D&A + legacy non-cash) | B28: =B15+B16 -> 3331.1822 | C28: =C15+C16 -> 3980.3534 | D28: =D15+D16 -> 4895.4253 | E28: =E15+E16 -> 6154.0037 | F28: =F15+F16 -> 7967.3627 | G28: =G15+G16 -> 10604.843 | H28: =H15+H16 -> 13063.073 | I28: =I15+I16 -> 15028.1 | ... K28: =K15+K16 -> 19073.595
A29: Less: cash taxes | B29: =B17 -> -20 | C29: =C17 -> -20 | D29: =D17 -> -20 | E29: =E17 -> -20 | F29: =F17 -> -20 | G29: =G17 -> -20 | H29: =H17 -> -20 | I29: =I17 -> -20 | ... K29: =K17 -> -20
A30: Less: capex | B30: =B19 -> -15303.96 | C30: =C19 -> -14667.841 | D30: =D19 -> -25099.018 | E30: =E19 -> -42514.427 | F30: =F19 -> -65274.957 | G30: =G19 -> -74853.85 | H30: =H19 -> -37384.249 | I30: =I19 -> -36012.332 | ... K30: =K19 -> -24206.66
A31: UNLEVERED FREE CASH FLOW | B31: =B28+B29+B30 -> -11992.778 | C31: =C28+C29+C30 -> -10707.488 | D31: =D28+D29+D30 -> -20223.593 | E31: =E28+E29+E30 -> -36380.423 | F31: =F28+F29+F30 -> -57327.594 | G31: =G28+G29+G30 -> -64269.007 | H31: =H28+H29+H30 -> -24341.176 | I31: =I28+I29+I30 -> -21004.232 | ... K31: =K28+K29+K30 -> -5153.0652
A32: Levered free cash flow (after interest) | B32: =B31+B14+B12 -> -11533.943 | C32: =C31+C14+C12 -> -10363.992 | D32: =D31+D14+D12 -> -19983.737 | E32: =E31+E14+E12 -> -36340.405 | F32: =F31+F14+F12 -> -57650.98 | G32: =G31+G14+G12 -> -65486.803 | H32: =H31+H14+H12 -> -26623.132 | I32: =I31+I14+I12 -> -23718.815 | ... K32: =K31+K14+K12 -> -8420.8379
A33: Excludes working capital and deferred revenue movements, which have historically been a source of cash for SpaceX. Unlevered FCF is the input to the DCF below.
A35: CREDIT CHECKS
A36: EBITDA / interest expense (coverage, x) | B36: =IFERROR(B28/-B14,"n/m") -> 6.1545523 | C36: =IFERROR(C28/-C14,"n/m") -> 7.3539338 | D36: =IFERROR(D28/-D14,"n/m") -> 9.0445822 | E36: =IFERROR(E28/-E14,"n/m") -> 11.369879 | F36: =IFERROR(F28/-F14,"n/m") -> 14.720165 | G36: =IFERROR(G28/-G14,"n/m") -> 7.7532351 | H36: =IFERROR(H28/-H14,"n/m") -> 5.3714254 | I36: =IFERROR(I28/-I14,"n/m") -> 5.2461749 | ... K36: =IFERROR(K28/-K14,"n/m") -> 5.580709
A37: Total debt / annualised EBITDA (leverage, x) | B37: =IFERROR(B24/(B28*4),"n/m") -> 2.9542065 | C37: =IFERROR(C24/(C28*4),"n/m") -> 2.4723935 | D37: =IFERROR(D24/(D28*4),"n/m") -> 2.0102441 | E37: =IFERROR(E24/(E28*4),"n/m") -> 1.5991216 | F37: =IFERROR(F24/(F28*4),"n/m") -> 2.831177 | G37: =IFERROR(G24/(G28*4),"n/m") -> 3.670843 | H37: =IFERROR(H24/(H28*4),"n/m") -> 3.4895693 | I37: =IFERROR(I24/(I28*4),"n/m") -> 3.4278586 | ... K37: =IFERROR(K24/(K28*4),"n/m") -> 2.946499
A38: Leverage within a 6.0x investment-grade-ish ceiling? | B38: =IF(ISNUMBER(B37),IF(B37<=6,"Yes","NO"),"n/m") -> Yes | C38: =IF(ISNUMBER(C37),IF(C37<=6,"Yes","NO"),"n/m") -> Yes | D38: =IF(ISNUMBER(D37),IF(D37<=6,"Yes","NO"),"n/m") -> Yes | E38: =IF(ISNUMBER(E37),IF(E37<=6,"Yes","NO"),"n/m") -> Yes | F38: =IF(ISNUMBER(F37),IF(F37<=6,"Yes","NO"),"n/m") -> Yes | G38: =IF(ISNUMBER(G37),IF(G37<=6,"Yes","NO"),"n/m") -> Yes | H38: =IF(ISNUMBER(H37),IF(H37<=6,"Yes","NO"),"n/m") -> Yes | I38: =IF(ISNUMBER(I37),IF(I37<=6,"Yes","NO"),"n/m") -> Yes | ... K38: =IF(ISNUMBER(K37),IF(K37<=6,"Yes","NO"),"n/m") -> Yes
A39: A 6.0x net-debt/EBITDA ceiling is a rough high-yield covenant marker, not a rating agency threshold. Where this reads NO, the capex plan is not fundable with debt alone on these earnings and would require equity or partner/SPV structures of the kind CoreWeave uses.
A41: DCF (read the terminal-value warning below before using this)
A42: WACC (annual) | B42: 0.115
A43: Terminal growth rate | B43: 0.04
A44: Normalised terminal-year FCF ($mm/yr) | B44: 40000
A45: PV of forecast unlevered FCF (Q3'26E-Q4'28E) | B45: =B31/(1+$B$42/4)^1+C31/(1+$B$42/4)^2+D31/(1+$B$42/4)^3+E31/(1+$B$42/4)^4+F31/(1+$B$42/4)^5+G31/(1+$B$42/4)^6+H31/(1+$B$42/4)^7+I31/(1+$B$42/4)^8+J31/(1+$B$42/4)^9+K31/(1+$B$42/4)^10 -> -222982.97
A46: PV of terminal value | B46: =$B$44*(1+$B$43)/($B$42-$B$43)/(1+$B$42)^2.5 -> 422517.69
A47: Enterprise value | B47: =B45+B46 -> 199534.72
A48: Equity value (EV less closing net debt) | B48: =B47-(K24-K22) -> -10266.59
A49: Terminal value as % of enterprise value | B49: =B46/B47 -> 2.1175147
A50: WARNING — READ BEFORE CITING THIS NUMBER. Forecast-period FCF is negative throughout, so the entire equity value rests on the terminal assumption, and the terminal-value share above will typically read well over 100% (the forecast period subtracts value). That makes this a restatement of the manually-entered normalised FCF cell, not an independent valuation. It is included because a cash-flow-based cross-check was requested, and it is more honest than the revenue-multiple and PEG blocks on the Consolidated P&L tab only in that its fragility is explicit. For a company mid-build with negative FCF, no DCF is informative: use it to test what steady-state cash flow would justify a given valuation, by changing the normalised FCF cell until equity value matches the market.
A52: This schedule closes two gaps flagged in the sanity check. (1) Depreciation: the forecast previously carried no charge for the new capex being spent, so operating income was overstated; new-capex depreciation is now an explicit Consolidated P&L line. (2) Financing: interest expense was previously a flat assumption unrelated to the debt implied by the capex plan. Debt is now drawn whenever cash would fall below the minimum buffer, and interest is charged on the actual balance. Both interest expense and interest income on the Consolidated P&L now link here. Simplifications: no working capital or deferred revenue movements, no debt repayment or refinancing, no equity issuance, and no asset retirements inside the window.

Sheet Balance Sheet & CF
A1: Balance Sheet & Cash Flow (Actuals)
A2: $ in millions. Source: SpaceX Q2 2026 earnings release, Consolidated Balance Sheets and Selected Cash Flow Information
A4: Balance Sheet, $mm | B4: Jun 30, 2026 | C4: Dec 31, 2025
A5: ASSETS
A6: Cash and cash equivalents | B6: 93522 | C6: 24747
A7: Marketable securities | B7: 6487 | C7: 0
A8: Accounts receivable, net | B8: 3596 | C8: 1579
A9: Inventory | B9: 2718 | C9: 2416
A10: Prepaid expenses and other current assets | B10: 1724 | C10: 2210
A11: Total current assets | B11: =SUM(B6:B10) -> 108047 | C11: =SUM(C6:C10) -> 30952
A12: Property, plant, and equipment, net | B12: 65736 | C12: 42602
A13: Finance lease right-of-use assets | B13: 1118 | C13: 1260
A14: Intangible assets, net | B14: 1318 | C14: 1548
A15: Digital assets | B15: 1098 | C15: 1637
A16: Goodwill | B16: 11645 | C16: 11809
A17: Deferred tax assets | B17: 354 | C17: 141
A18: Other assets | B18: 3454 | C18: 2130
A19: Total assets | B19: =B11+SUM(B12:B18) -> 192770 | C19: =C11+SUM(C12:C18) -> 92079
A21: LIABILITIES
A22: Accounts payable | B22: 8243 | C22: 11792
A23: Deferred revenue, current | B23: 7977 | C23: 6111
A24: Debt and finance leases, current | B24: 2525 | C24: 928
A25: Accrued expenses and other current liabilities | B25: 2377 | C25: 2569
A26: Total current liabilities | B26: =SUM(B22:B25) -> 21122 | C26: =SUM(C22:C25) -> 21400
A27: Deferred revenue, net of current | B27: 6309 | C27: 6005
A28: Debt and finance leases, net of current | B28: 36839 | C28: 21968
A29: Other liabilities | B29: 1276 | C29: 1381
A30: Total liabilities | B30: =B26+SUM(B27:B29) -> 65546 | C30: =C26+SUM(C27:C29) -> 50754
A32: REDEEMABLE CONVERTIBLE PREFERRED STOCK & EQUITY
A33: Redeemable convertible preferred stock | B33: 0 | C33: 38752
A34: Total shareholders' equity | B34: 127224 | C34: 2573
A35: Total liabilities, preferred stock & equity | B35: =B30+B33+B34 -> 192770 | C35: =C30+C33+C34 -> 92079
A36: Balance check (Assets - Liab&Equity) | B36: =B19-B35 -> 0 | C36: =C19-C35 -> 0
A39: Cash Flow (6 months ended June 30), $mm | B39: 2026 | C39: 2025
A40: Net cash provided by operating activities | B40: 3466 | C40: 351
A41: Net cash used in investing activities | B41: -34487 | C41: -6032
A42: Net cash provided by financing activities | B42: 100291 | C42: 9199
A43: Net change in cash & restricted cash | B43: =SUM(B40:B42) -> 69270 | C43: =SUM(C40:C42) -> 3518
A44: Cash & restricted cash, beginning of period | B44: 25124 | C44: 11501
A45: Cash & restricted cash, end of period | B45: =B43+B44 -> 94394 | C45: =C43+C44 -> 15019
A47: Key financing events: IPO closed June 12, 2026 (638.9mm Class A shares, ~$85.7B net proceeds); $25B senior notes issued June 26, 2026 (5 tranches, 2031-2056, weighted avg rate 5.855%).

Sheet Terrestrial vs Orbital
A1: Capex per GW of AI Compute: Terrestrial vs Orbital
A2: $ in millions per GW of AVERAGE compute power. Bottom-up build from SpaceX's disclosed AI1 specifications and published Starship launch economics. Memo/analysis tab — does not feed the forecast.
A4: $mm per GW (average compute) | B4: Terrestrial | C4: Orbital | E4: Basis / source
A5: PHYSICAL INPUTS (editable)
A6: Average compute power per satellite (kW) | B6: n/a | C6: 120 | E6: SpaceX AI1 disclosure (Jun 8, 2026): 150 kW peak, 120 kW average compute payload. Average is the right basis since revenue tracks delivered compute.
A7: Compute power density (kW per ton) | B7: n/a | C7: 70 | E7: AI1 disclosed spec: 70 kW per ton. Musk's forward-looking claim of 100 kW/ton is tested in the sensitivity grid below.
A8: Launch cost ($ per kg to LEO) | B8: n/a | C8: 200 | E8: Starship target range is roughly $100-500/kg once fully reusable; Musk's aspiration is ~$10/kg. Falcon 9 today is ~$2,700-3,000/kg. $200/kg used as the base case.
A9: Solar array cost ($ per W) | B9: n/a | C9: 1.5 | E9: AI1 carries a 150 kW array at 250 W/m², using SpaceX-manufactured cells from its Bastrop facility. Assumes mass-production economics well below traditional space-solar costs.
A10: Radiator cost ($ per m2) | B10: n/a | C10: 4000 | E10: AI1 carries a 110 m² deployable liquid radiator with redundant pumping loops and micrometeoroid shielding.
A11: Radiator area per satellite (m2) | B11: n/a | C11: 110 | E11: AI1 disclosed spec.
A12: Satellite bus / structure / integration ($mm each) | B12: n/a | C12: 1.2 | E12: Structure, avionics, propulsion, deployment mechanisms and assembly, excluding compute, solar and radiator. Benchmarked up from Starlink V2 unit economics for a larger, more complex spacecraft.
A13: Space-qualification premium on compute hardware | B13: n/a | C13: 1.3 | E13: Radiation tolerance, thermal packaging and lower production volumes versus commodity data-centre racks.
A14: Compute hardware cost, terrestrial basis ($mm per GW) | B14: 23000 | C14: n/a | E14: Epoch AI puts servers/GPUs at ~60% of a $38B/GW build; Bernstein's rack build-up ($3.4M compute of a $5.9M GB200 NVL72 rack) implies ~$24B/GW. Orbital applies the premium above to this same figure.
A15: Building, land & site works ($mm per GW) | B15: 4000 | C15: 0 | E15: Eliminated in orbit — no land, no shell, no zoning.
A16: Grid power delivery & backup ($mm per GW) | B16: 6500 | C16: 0 | E16: Substation, transformers, UPS and backup generation. Eliminated in orbit: the solar array below replaces it, and sunlight is free.
A17: Cooling plant & water systems ($mm per GW) | B17: 4500 | C17: 0 | E17: Chillers, CRAHs, liquid loops and water infrastructure. Eliminated in orbit: replaced by the radiator line below, though vacuum makes heat rejection harder, not easier, per unit area.
A18: Ground segment / optical links ($mm per GW) | B18: 0 | C18: 1500 | E18: Orbital needs laser inter-satellite links and ground gateways to move data; terrestrial fibre is assumed included in site works.
A20: DERIVED PHYSICAL QUANTITIES (orbital)
A21: Satellites required per GW | B21: n/a | C21: =1000000/C6 -> 8333.3333 | E21: 1 GW of average compute divided by 120 kW per satellite. Musk noted one AI1 is roughly equivalent to a single NVIDIA GB300 rack.
A22: Mass to orbit per GW (metric tons) | B22: n/a | C22: =1000000/C7 -> 14285.714 | E22: 1 GW divided by 70 kW/ton. For scale, this is well above SpaceX's total mass launched to date in a year — the build-out is launch-cadence constrained, not just capital constrained.
A24: CAPEX BUILD-UP PER GW
A25: Compute hardware | B25: =B14 -> 23000 | C25: =B14*C13 -> 29900 | E25: The dominant cost on both sides, and the one orbital cannot avoid.
A26: Building, land & site works | B26: =B15 -> 4000 | C26: =C15 -> 0 | E26: Orbital saving.
A27: Grid power delivery & backup | B27: =B16 -> 6500 | C27: =C16 -> 0 | E27: Orbital saving — this is the 'free energy' advantage in capex terms.
A28: Cooling plant & water systems | B28: =B17 -> 4500 | C28: =C17 -> 0 | E28: Orbital saving on paper, but see the radiator line — heat rejection is replaced, not removed.
A29: Solar array (replaces grid power) | B29: =0 -> 0 | C29: =C21*150*1000*C9/1000000 -> 1875 | E29: 150 kW array per satellite at the $/W input. This is the capex you pay to get 'free' energy.
A30: Deployable radiators (replace cooling) | B30: =0 -> 0 | C30: =C21*C11*C10/1000000 -> 3666.6667 | E30: 110 m² per satellite. Vacuum removes water and chiller cost but radiative heat rejection needs large deployable area — several independent analyses argue AI1's disclosed radiator area is the binding physical constraint on the design.
A31: Satellite bus, structure & integration | B31: =0 -> 0 | C31: =C21*C12 -> 10000 | E31: No terrestrial analogue — this is pure incremental cost for orbital.
A32: Launch to LEO | B32: =0 -> 0 | C32: =C22*C8/1000 -> 2857.1429 | E32: Mass per GW times $/kg. Notably NOT the dominant term at Starship target pricing.
A33: Ground segment / optical links | B33: =B18 -> 0 | C33: =C18 -> 1500 | E33: Orbital-only cost.
A34: TOTAL CAPEX PER GW | B34: =SUM(B25:B33) -> 38000 | C34: =SUM(C25:C33) -> 49798.81 | E34: Cross-check: Epoch AI's independent 1 GW model lands at $38B for terrestrial; Bernstein $35B, Nvidia $50-60B, Orennia $60B. The orbital figure has no external benchmark — it is built from SpaceX's own disclosed specs.
A35: Orbital as a multiple of terrestrial | C35: =C34/B34 -> 1.310495
A37: ANNUALIZED COST OF OWNERSHIP PER GW (where free energy actually shows up)
A38: Compute hardware life (years) | B38: 5 | C38: 5 | E38: Epoch AI assumes 5 years for IT equipment on the ground. Assumed equal in orbit — chip obsolescence, not wear, is the binding constraint.
A39: Infrastructure life (years) | B39: 14 | C39: 5 | E39: THE CRITICAL ASYMMETRY. A terrestrial building, substation and chiller plant serve ~14 years and multiple server refreshes. An orbital satellite cannot be serviced — refreshing the compute means relaunching the entire spacecraft, so ALL of it is written off on the compute cycle.
A40: Annual energy cost ($mm per GW per year) | B40: 600 | C40: 0 | E40: Epoch AI puts energy at ~$0.6B/yr for a 1 GW facility. Zero in orbit — this is the headline 'free energy' saving.
A41: Other annual opex ($mm per GW per year) | B41: 300 | C41: 150 | E41: Terrestrial: water, maintenance, staffing. Orbital: ground stations and constellation operations. Musk claims 'no ongoing operational or maintenance needs' in orbit; a residual is assumed here.
A43: Annualized compute hardware | B43: =B25/B38 -> 4600 | C43: =C25/C38 -> 5980
A44: Annualized infrastructure (all non-compute capex) | B44: =(B34-B25)/B39 -> 1071.4286 | C44: =(C34-C25)/C39 -> 3979.7619 | E44: Terrestrial spreads this over 14 years; orbital over 5. This single line drives most of the result.
A45: Energy | B45: =B40 -> 600 | C45: =C40 -> 0
A46: Other opex | B46: =B41 -> 300 | C46: =C41 -> 150
A47: TOTAL ANNUALIZED COST PER GW | B47: =SUM(B43:B46) -> 6571.4286 | C47: =SUM(C43:C46) -> 10109.762
A48: Orbital as a multiple of terrestrial | C48: =C47/B47 -> 1.538442
A49: Orbital satellite life needed to match terrestrial (years) | C49: =(C34-C25)/(B47-C40-C41-C25/C38) -> 45.078209 | E49: Holding everything else fixed, this is the on-orbit service life at which orbital annualized cost equals terrestrial. Longer-lived satellites are the single biggest lever — bigger than launch cost.
A51: SENSITIVITY: ORBITAL CAPEX PER GW ($mm)
A52: Power density (kW/ton) \ Launch cost ($/kg) | B52: 10 | C52: 100 | D52: 200 | E52: 500 | F52: 1000
A53: 50 | B53: =(C34-C32)+(1000000/$A53)*B$52/1000 -> 47141.667 | C53: =(C34-C32)+(1000000/$A53)*C$52/1000 -> 48941.667 | D53: =(C34-C32)+(1000000/$A53)*D$52/1000 -> 50941.667 | E53: =(C34-C32)+(1000000/$A53)*E$52/1000 -> 56941.667 | F53: =(C34-C32)+(1000000/$A53)*F$52/1000 -> 66941.667
A54: 70 | B54: =(C34-C32)+(1000000/$A54)*B$52/1000 -> 47084.524 | C54: =(C34-C32)+(1000000/$A54)*C$52/1000 -> 48370.238 | D54: =(C34-C32)+(1000000/$A54)*D$52/1000 -> 49798.81 | E54: =(C34-C32)+(1000000/$A54)*E$52/1000 -> 54084.524 | F54: =(C34-C32)+(1000000/$A54)*F$52/1000 -> 61227.381
A55: 100 | B55: =(C34-C32)+(1000000/$A55)*B$52/1000 -> 47041.667 | C55: =(C34-C32)+(1000000/$A55)*C$52/1000 -> 47941.667 | D55: =(C34-C32)+(1000000/$A55)*D$52/1000 -> 48941.667 | E55: =(C34-C32)+(1000000/$A55)*E$52/1000 -> 51941.667 | F55: =(C34-C32)+(1000000/$A55)*F$52/1000 -> 56941.667
A56: 150 | B56: =(C34-C32)+(1000000/$A56)*B$52/1000 -> 47008.333 | C56: =(C34-C32)+(1000000/$A56)*C$52/1000 -> 47608.333 | D56: =(C34-C32)+(1000000/$A56)*D$52/1000 -> 48275 | E56: =(C34-C32)+(1000000/$A56)*E$52/1000 -> 50275 | F56: =(C34-C32)+(1000000/$A56)*F$52/1000 -> 53608.333
A57: Only the launch component varies in this grid; all other orbital costs are fixed by satellite count, which is set by kW per satellite rather than kW per ton. Terrestrial comparison point is the total above.
A59: READ-ACROSS
A60: Launch cost is not the binding constraint. At the $200/kg Starship target, getting a full gigawatt of compute to orbit costs only a few billion dollars — a modest share of the total. Even at Musk's aspirational $10/kg, the orbital total barely moves, because the cost sits in the hardware, not the ride.
A61: Free energy and no water cooling are real but second-order. They remove the grid, backup generation and chiller plant from capex, and roughly $0.6B/GW/year of energy opex. Against that, orbital must add solar arrays, deployable radiators, a satellite bus and launch — which together cost more than what they replace.
A62: The decisive variable is service life. A terrestrial data centre amortizes its shell, power and cooling over ~14 years across several server refreshes. A satellite cannot be serviced, so refreshing compute means rebuilding and relaunching everything. Writing the whole spacecraft off on a 5-year compute cycle is what makes orbital more expensive per year, despite the free power.
A63: Implication for the forecast: the $55B/GW orbital placeholder used on the Assumptions tab is broadly consistent with this bottom-up build, so the model's orbital memo block is not obviously mis-sized. But orbital does not look cheaper than terrestrial on these inputs, which is the opposite of the case usually made for it.
A64: Caveats: no external benchmark exists for orbital capex per GW — every figure on that side is derived from SpaceX's own disclosed specs and reasonable unit-cost assumptions. Several independent analyses have questioned whether AI1's disclosed radiator area can reject the heat its stated compute payload generates at all; if it cannot, radiator cost and mass both rise materially and the comparison worsens further.

Sheet Scenarios to 2030
A1: Revenue Scenarios to 2030 — What Would Have To Be True
A2: $ in billions, calendar years. Each scenario takes a revenue path as the input and solves BACKWARDS for the compute, capex, funding and launch cadence required to deliver it.
A4: $B (calendar year) | B4: 2026E | C4: 2027E | D4: 2028E | E4: 2029E | F4: 2030E | H4: Basis / source
A5: SHARED UNIT ECONOMICS (editable — applied identically to every scenario)
A6: Revenue per revenue-generating GW ($B/yr) | B6: 11.6 | C6: 11 | D6: 9.6 | E6: 9 | F6: 8.5 | H6: Carried from the Segment Forecast tab's recalibrated $/GW rate, which sits near CoreWeave's implied ~$10.9B/GW/yr. Declines as installed capacity outpaces contracted utilisation.
A7: Monetizable share of compute (%) | B7: 0.9 | C7: 0.9 | D7: 0.9 | E7: 0.9 | F7: 0.9 | H7: Management indicated roughly 10% of compute goes to internal Grok training and earns no external revenue.
A8: Capex per incremental GW ($B/GW) | B8: 30 | C8: 25 | D8: 22 | E8: 20 | F8: 19 | H8: Recalibrated against Bernstein ($35B), Epoch AI ($38B), Nvidia ($50-60B) and CoreWeave's implied ~$46B/GW. Declines only gently — external sources describe per-GW build costs as flat-to-rising.
A9: Non-AI capex as % of non-AI revenue | B9: 0.4 | C9: 0.38 | D9: 0.35 | E9: 0.33 | F9: 0.32 | H9: Space plus Connectivity capex intensity, benchmarked to Q2'26A actuals.
A10: EBITDA margin (%) | B10: 0.14 | C10: 0.2 | D10: 0.25 | E10: 0.28 | F10: 0.3 | H10: Used only to size the external funding gap. Q2'26A Adjusted EBITDA margin was 45%, but that predates the depreciation load from the build-out.
A12: PHYSICAL CONSTANTS
A13: Nameplate compute at end-2025 (GW) | B13: 1 | H13: SpaceX reported 1.0 GW at Q1'26A and 1.4 GW at Q2'26A.
A14: US average electricity demand (GW) | B14: 460 | H14: Approximate average (not peak) US electricity draw, for scale only.
A15: Global data centre capacity, all workloads (GW) | B15: 60 | H15: Rough industry estimate of total installed capacity across all workloads, not just AI.
A16: Mass to orbit per GW (tons) | B16: 14286 | H16: From the Terrestrial vs Orbital tab: 1 GW divided by AI1's disclosed 70 kW/ton.
A17: Starship payload to LEO per launch (tons) | B17: 200 | H17: Block 4 design payload. Block 3 is 100t; using the higher figure is the generous assumption.
A19: SCENARIO A — BASE (this model, extended)
A20: Total revenue ($B) << INPUT | B20: 36 | C20: 98 | D20: 169 | E20: 236 | F20: 307 | H20: 2026-2028 are this workbook's own quarterly forecast summed to calendar years. 2029-2030 extend it at decelerating growth (+40%, +30%).
A21: AI share of revenue (%) << INPUT | B21: 0.55 | C21: 0.68 | D21: 0.72 | E21: 0.75 | F21: 0.76 | H21: Morgan Stanley attributes roughly $190B of its $330B 2030 estimate to AI; these paths assume AI carries a rising majority.
A22: AI revenue ($B) | B22: =B20*B21 -> 19.8 | C22: =C20*C21 -> 66.64 | D22: =D20*D21 -> 121.68 | E22: =E20*E21 -> 177 | F22: =F20*F21 -> 233.32
A23: Revenue-generating compute required (GW) | B23: =B22/B6 -> 1.7068966 | C23: =C22/C6 -> 6.0581818 | D23: =D22/D6 -> 12.675 | E23: =E22/E6 -> 19.666667 | F23: =F22/F6 -> 27.449412 | H23: AI revenue divided by revenue per GW — this is the compute that must actually be earning.
A24: NAMEPLATE COMPUTE REQUIRED (GW) | B24: =B23/B7 -> 1.8965517 | C24: =C23/C7 -> 6.7313131 | D24: =D23/D7 -> 14.083333 | E24: =E23/E7 -> 21.851852 | F24: =F23/F7 -> 30.499346 | H24: Grossed up for the internal Grok allocation. This is the physical capacity that must be built, powered and cooled.
A25: Incremental GW added in year | B25: =B24-$B$13 -> 0.89655172 | C25: =C24-B24 -> 4.8347614 | D25: =D24-C24 -> 7.3520202 | E25: =E24-D24 -> 7.7685185 | F25: =F24-E24 -> 8.6474946
A26: AI capex ($B) | B26: =MAX(0,B25)*B8 -> 26.896552 | C26: =MAX(0,C25)*C8 -> 120.86904 | D26: =MAX(0,D25)*D8 -> 161.74444 | E26: =MAX(0,E25)*E8 -> 155.37037 | F26: =MAX(0,F25)*F8 -> 164.3024
A27: Non-AI capex ($B) | B27: =(B20-B22)*B9 -> 6.48 | C27: =(C20-C22)*C9 -> 11.9168 | D27: =(D20-D22)*D9 -> 16.562 | E27: =(E20-E22)*E9 -> 19.47 | F27: =(F20-F22)*F9 -> 23.5776
A28: Total capex ($B) | B28: =B26+B27 -> 33.376552 | C28: =C26+C27 -> 132.78584 | D28: =D26+D27 -> 178.30644 | E28: =E26+E27 -> 174.84037 | F28: =F26+F27 -> 187.88
A29: Cumulative capex from 2026 ($B) | B29: =B28 -> 33.376552 | C29: =B29+C28 -> 166.16239 | D29: =C29+D28 -> 344.46883 | E29: =D29+E28 -> 519.3092 | F29: =E29+F28 -> 707.1892
A30: EBITDA ($B) | B30: =B20*B10 -> 5.04 | C30: =C20*C10 -> 19.6 | D30: =D20*D10 -> 42.25 | E30: =E20*E10 -> 66.08 | F30: =F20*F10 -> 92.1
A31: CUMULATIVE EXTERNAL FUNDING NEEDED ($B) | B31: =MAX(0,B28-B30) -> 28.336552 | C31: =MAX(0,B31+C28-C30) -> 141.52239 | D31: =MAX(0,C31+D28-D30) -> 277.57883 | E31: =MAX(0,D31+E28-E30) -> 386.3392 | F31: =MAX(0,E31+F28-F30) -> 482.1192 | H31: Capex less EBITDA, cumulated. Ignores working capital and existing cash, so it understates rather than overstates the need.
A32: Nameplate GW as % of US average power demand | B32: =B24/$B$14 -> 0.0041229385 | C32: =C24/$B$14 -> 0.014633289 | D32: =D24/$B$14 -> 0.030615942 | E32: =E24/$B$14 -> 0.047504026 | F32: =F24/$B$14 -> 0.066302927
A33: Nameplate GW vs today's global data centre capacity | B33: =B24/$B$15 -> 0.031609195 | C33: =C24/$B$15 -> 0.11218855 | D33: =D24/$B$15 -> 0.23472222 | E33: =E24/$B$15 -> 0.36419753 | F33: =F24/$B$15 -> 0.50832244
A34: Starship launches per DAY if built in orbit | B34: =MAX(0,B25)*$B$16/$B$17/365 -> 0.17545394 | C34: =MAX(0,C25)*$B$16/$B$17/365 -> 0.94615618 | D34: =MAX(0,D25)*$B$16/$B$17/365 -> 1.4387803 | E34: =MAX(0,E25)*$B$16/$B$17/365 -> 1.5202884 | F34: =MAX(0,F25)*$B$16/$B$17/365 -> 1.6923028 | H34: Feasibility check only — assumes the year's incremental capacity is delivered to orbit rather than on the ground. SpaceX has flown 78 launches so far in 2026, about 0.4 per day.
A36: SCENARIO B — STREET (Goldman Sachs / Morgan Stanley)
A37: Total revenue ($B) << INPUT | B37: 36 | C37: 75 | D37: 160 | E37: 207 | F37: 400 | H37: Morgan Stanley models $160B in 2028 and $330B in 2030; Goldman Sachs $470B in 2030; FactSet consensus is near $207B for 2029. 2030 shown at the $400B midpoint of the two banks.
A38: AI share of revenue (%) << INPUT | B38: 0.55 | C38: 0.68 | D38: 0.72 | E38: 0.75 | F38: 0.76 | H38: Morgan Stanley attributes roughly $190B of its $330B 2030 estimate to AI; these paths assume AI carries a rising majority.
A39: AI revenue ($B) | B39: =B37*B38 -> 19.8 | C39: =C37*C38 -> 51 | D39: =D37*D38 -> 115.2 | E39: =E37*E38 -> 155.25 | F39: =F37*F38 -> 304
A40: Revenue-generating compute required (GW) | B40: =B39/B6 -> 1.7068966 | C40: =C39/C6 -> 4.6363636 | D40: =D39/D6 -> 12 | E40: =E39/E6 -> 17.25 | F40: =F39/F6 -> 35.764706 | H40: AI revenue divided by revenue per GW — this is the compute that must actually be earning.
A41: NAMEPLATE COMPUTE REQUIRED (GW) | B41: =B40/B7 -> 1.8965517 | C41: =C40/C7 -> 5.1515152 | D41: =D40/D7 -> 13.333333 | E41: =E40/E7 -> 19.166667 | F41: =F40/F7 -> 39.738562 | H41: Grossed up for the internal Grok allocation. This is the physical capacity that must be built, powered and cooled.
A42: Incremental GW added in year | B42: =B41-$B$13 -> 0.89655172 | C42: =C41-B41 -> 3.2549634 | D42: =D41-C41 -> 8.1818182 | E42: =E41-D41 -> 5.8333333 | F42: =F41-E41 -> 20.571895
A43: AI capex ($B) | B43: =MAX(0,B42)*B8 -> 26.896552 | C43: =MAX(0,C42)*C8 -> 81.374086 | D43: =MAX(0,D42)*D8 -> 180 | E43: =MAX(0,E42)*E8 -> 116.66667 | F43: =MAX(0,F42)*F8 -> 390.86601
A44: Non-AI capex ($B) | B44: =(B37-B39)*B9 -> 6.48 | C44: =(C37-C39)*C9 -> 9.12 | D44: =(D37-D39)*D9 -> 15.68 | E44: =(E37-E39)*E9 -> 17.0775 | F44: =(F37-F39)*F9 -> 30.72
A45: Total capex ($B) | B45: =B43+B44 -> 33.376552 | C45: =C43+C44 -> 90.494086 | D45: =D43+D44 -> 195.68 | E45: =E43+E44 -> 133.74417 | F45: =F43+F44 -> 421.58601
A46: Cumulative capex from 2026 ($B) | B46: =B45 -> 33.376552 | C46: =B46+C45 -> 123.87064 | D46: =C46+D45 -> 319.55064 | E46: =D46+E45 -> 453.2948 | F46: =E46+F45 -> 874.88082
A47: EBITDA ($B) | B47: =B37*B10 -> 5.04 | C47: =C37*C10 -> 15 | D47: =D37*D10 -> 40 | E47: =E37*E10 -> 57.96 | F47: =F37*F10 -> 120
A48: CUMULATIVE EXTERNAL FUNDING NEEDED ($B) | B48: =MAX(0,B45-B47) -> 28.336552 | C48: =MAX(0,B48+C45-C47) -> 103.83064 | D48: =MAX(0,C48+D45-D47) -> 259.51064 | E48: =MAX(0,D48+E45-E47) -> 335.2948 | F48: =MAX(0,E48+F45-F47) -> 636.88082 | H48: Capex less EBITDA, cumulated. Ignores working capital and existing cash, so it understates rather than overstates the need.
A49: Nameplate GW as % of US average power demand | B49: =B41/$B$14 -> 0.0041229385 | C49: =C41/$B$14 -> 0.011198946 | D49: =D41/$B$14 -> 0.028985507 | E49: =E41/$B$14 -> 0.041666667 | F49: =F41/$B$14 -> 0.086388178
A50: Nameplate GW vs today's global data centre capacity | B50: =B41/$B$15 -> 0.031609195 | C50: =C41/$B$15 -> 0.085858586 | D50: =D41/$B$15 -> 0.22222222 | E50: =E41/$B$15 -> 0.31944444 | F50: =F41/$B$15 -> 0.66230937
A51: Starship launches per DAY if built in orbit | B51: =MAX(0,B42)*$B$16/$B$17/365 -> 0.17545394 | C51: =MAX(0,C42)*$B$16/$B$17/365 -> 0.63699188 | D51: =MAX(0,D42)*$B$16/$B$17/365 -> 1.6011706 | E51: =MAX(0,E42)*$B$16/$B$17/365 -> 1.1415753 | F51: =MAX(0,F42)*$B$16/$B$17/365 -> 4.0258918 | H51: Feasibility check only — assumes the year's incremental capacity is delivered to orbit rather than on the ground. SpaceX has flown 78 launches so far in 2026, about 0.4 per day.
A53: SCENARIO C — MUSK ($1 TRILLION BY 2030)
A54: Total revenue ($B) << INPUT | B54: 36 | C54: 130 | D54: 290 | E54: 600 | F54: 1000 | H54: Musk told analysts on the Q2'26 call that internal projections for $1 trillion of revenue — 'not ARR, but revenue' — moved from 2031 to 2030, with a non-zero chance of 2029. Intermediate years are a smooth path fitted to that endpoint.
A55: AI share of revenue (%) << INPUT | B55: 0.55 | C55: 0.72 | D55: 0.78 | E55: 0.8 | F55: 0.8 | H55: Morgan Stanley attributes roughly $190B of its $330B 2030 estimate to AI; these paths assume AI carries a rising majority.
A56: AI revenue ($B) | B56: =B54*B55 -> 19.8 | C56: =C54*C55 -> 93.6 | D56: =D54*D55 -> 226.2 | E56: =E54*E55 -> 480 | F56: =F54*F55 -> 800
A57: Revenue-generating compute required (GW) | B57: =B56/B6 -> 1.7068966 | C57: =C56/C6 -> 8.5090909 | D57: =D56/D6 -> 23.5625 | E57: =E56/E6 -> 53.333333 | F57: =F56/F6 -> 94.117647 | H57: AI revenue divided by revenue per GW — this is the compute that must actually be earning.
A58: NAMEPLATE COMPUTE REQUIRED (GW) | B58: =B57/B7 -> 1.8965517 | C58: =C57/C7 -> 9.4545455 | D58: =D57/D7 -> 26.180556 | E58: =E57/E7 -> 59.259259 | F58: =F57/F7 -> 104.57516 | H58: Grossed up for the internal Grok allocation. This is the physical capacity that must be built, powered and cooled.
A59: Incremental GW added in year | B59: =B58-$B$13 -> 0.89655172 | C59: =C58-B58 -> 7.5579937 | D59: =D58-C58 -> 16.72601 | E59: =E58-D58 -> 33.078704 | F59: =F58-E58 -> 45.315904
A60: AI capex ($B) | B60: =MAX(0,B59)*B8 -> 26.896552 | C60: =MAX(0,C59)*C8 -> 188.94984 | D60: =MAX(0,D59)*D8 -> 367.97222 | E60: =MAX(0,E59)*E8 -> 661.57407 | F60: =MAX(0,F59)*F8 -> 861.00218
A61: Non-AI capex ($B) | B61: =(B54-B56)*B9 -> 6.48 | C61: =(C54-C56)*C9 -> 13.832 | D61: =(D54-D56)*D9 -> 22.33 | E61: =(E54-E56)*E9 -> 39.6 | F61: =(F54-F56)*F9 -> 64
A62: Total capex ($B) | B62: =B60+B61 -> 33.376552 | C62: =C60+C61 -> 202.78184 | D62: =D60+D61 -> 390.30222 | E62: =E60+E61 -> 701.17407 | F62: =F60+F61 -> 925.00218
A63: Cumulative capex from 2026 ($B) | B63: =B62 -> 33.376552 | C63: =B63+C62 -> 236.15839 | D63: =C63+D62 -> 626.46062 | E63: =D63+E62 -> 1327.6347 | F63: =E63+F62 -> 2252.6369
A64: EBITDA ($B) | B64: =B54*B10 -> 5.04 | C64: =C54*C10 -> 26 | D64: =D54*D10 -> 72.5 | E64: =E54*E10 -> 168 | F64: =F54*F10 -> 300
A65: CUMULATIVE EXTERNAL FUNDING NEEDED ($B) | B65: =MAX(0,B62-B64) -> 28.336552 | C65: =MAX(0,B65+C62-C64) -> 205.11839 | D65: =MAX(0,C65+D62-D64) -> 522.92062 | E65: =MAX(0,D65+E62-E64) -> 1056.0947 | F65: =MAX(0,E65+F62-F64) -> 1681.0969 | H65: Capex less EBITDA, cumulated. Ignores working capital and existing cash, so it understates rather than overstates the need.
A66: Nameplate GW as % of US average power demand | B66: =B58/$B$14 -> 0.0041229385 | C66: =C58/$B$14 -> 0.02055336 | D66: =D58/$B$14 -> 0.056914251 | E66: =E58/$B$14 -> 0.12882448 | F66: =F58/$B$14 -> 0.22733731
A67: Nameplate GW vs today's global data centre capacity | B67: =B58/$B$15 -> 0.031609195 | C67: =C58/$B$15 -> 0.15757576 | D67: =D58/$B$15 -> 0.43634259 | E67: =E58/$B$15 -> 0.98765432 | F67: =F58/$B$15 -> 1.7429194
A68: Starship launches per DAY if built in orbit | B68: =MAX(0,B59)*$B$16/$B$17/365 -> 0.17545394 | C68: =MAX(0,C59)*$B$16/$B$17/365 -> 1.479089 | D68: =MAX(0,D59)*$B$16/$B$17/365 -> 3.2732573 | E68: =MAX(0,E59)*$B$16/$B$17/365 -> 6.473457 | F68: =MAX(0,F59)*$B$16/$B$17/365 -> 8.8682604 | H68: Feasibility check only — assumes the year's incremental capacity is delivered to orbit rather than on the ground. SpaceX has flown 78 launches so far in 2026, about 0.4 per day.
A70: 2030 SIDE-BY-SIDE
B71: Base | C71: Street | D71: Musk
A72: Revenue ($B) | B72: =F20 -> 307 | C72: =F37 -> 400 | D72: =F54 -> 1000
A73: Nameplate compute required (GW) | B73: =F24 -> 30.499346 | C73: =F41 -> 39.738562 | D73: =F58 -> 104.57516
A74: Capex in 2030 alone ($B) | B74: =F28 -> 187.88 | C74: =F45 -> 421.58601 | D74: =F62 -> 925.00218
A75: Cumulative capex 2026-2030 ($B) | B75: =F29 -> 707.1892 | C75: =F46 -> 874.88082 | D75: =F63 -> 2252.6369
A76: Cumulative external funding needed ($B) | B76: =F31 -> 482.1192 | C76: =F48 -> 636.88082 | D76: =F65 -> 1681.0969
A77: Share of US average power demand | B77: =F32 -> 0.066302927 | C77: =F49 -> 0.086388178 | D77: =F66 -> 0.22733731
A78: Multiple of global data centre capacity | B78: =F33 -> 0.50832244 | C78: =F50 -> 0.66230937 | D78: =F67 -> 1.7429194
A79: Starship launches per day if orbital | B79: =F34 -> 1.6923028 | C79: =F51 -> 4.0258918 | D79: =F68 -> 8.8682604
A81: READ-ACROSS
A82: This model is not conservative relative to the people who underwrote the IPO. Its 2028 revenue of $169B sits above Morgan Stanley's $160B, and its exit run-rate implies a 2029 above the ~$207B FactSet consensus. It is conservative only against Musk's own aspiration, which both lead banks model at roughly a third.
A83: The $1 trillion case does not fail on financial assumptions — it fails on physics. Delivering it requires roughly 90 GW of nameplate compute, which is around a fifth of average total US electricity demand and more than the entire world's installed data centre capacity across all workloads today.
A84: Capital is the second binding constraint. The Musk path needs on the order of $1.5 trillion of cumulative capex between 2026 and 2030, against a company that raised $86 billion at IPO and whose shares fell 14% when quarterly capex came in at $18 billion.
A85: The orbital route does not relieve the constraint, it relocates it. Building the incremental capacity in space at AI1's disclosed 70 kW/ton implies a Starship cadence measured in dozens of launches per day, against roughly 0.4 per day today. And per the Terrestrial vs Orbital tab, orbital costs more per GW-year, not less.
A86: How to use this tab: the revenue rows are inputs and everything below them is solved. Rather than debating whether a revenue number is too low, change it and read off what it demands in gigawatts, dollars and launches — then judge whether that is deliverable. The unit economics are deliberately held identical across all three scenarios so the comparison isolates scale, not assumptions.

Sheet Model vs Brian Wang
A1: This Model vs Brian Wang / NextBigFuture
A2: $ in billions. Wang's published SpaceX calls compared to this model, plus the bridge showing exactly what would have to change to reach them. His Tesla calls are shown separately for context — they are not comparable to a SpaceX model line-by-line.
A4: Metric | B4: This model | C4: Brian Wang | D4: Difference | F4: Source / comment
A5: SPACEX — HEAD TO HEAD (directly comparable)
A6: End-2026 revenue run-rate ($B) | B6: 51.2 | C6: 82 | D6: =IFERROR(C6/B6,"n/a") -> 1.6015625 | F6: Wang's published base case was $82B ARR for end-2026, with a bull case near $96B. SpaceX then guided to $100B+ ARR by December — so Wang was LOW, and this model is lower still. Note ARR (contracted run-rate) and GAAP revenue are not the same measure; this comparison is indicative.
A7: End-2027 revenue run-rate ($B) | B7: 139.6 | C7: 300 | D7: =IFERROR(C7/B7,"n/a") -> 2.1489971 | F7: Wang: '$300 billion per year by end of 2027', and he notes SemiAnalysis reached the same figure independently. This model's Q4'27E revenue annualised is $139.6B — about 47% of his number.
A8: 2030 revenue ($B) | B8: 307 | C8: 1000 | D8: =IFERROR(C8/B8,"n/a") -> 3.257329 | F8: Wang has SpaceX above $1 trillion in 2030, matching Musk's own revised target. Morgan Stanley is at $330B and Goldman Sachs at $470B. Model figure is the Base scenario from the Scenarios to 2030 tab.
A9: Nameplate compute at end-2027 (GW) | B9: 10 | C9: 10 | D9: =IFERROR(C9/B9,"n/a") -> 1 | F9: This model reaches 10.0 GW at Q4'27E, and Wang and SemiAnalysis both work from a roughly 10 GW end-2027 base. The two sides AGREE on capacity — which is what makes the revenue gap below so informative.
A10: Implied revenue per nameplate GW ($B/yr) | B10: =B7*0.72/B9 -> 10.0512 | C10: =C7*0.72/C9 -> 21.6 | D10: =IFERROR(C10/B10,"n/a") -> 2.1489971 | F10: THE CRUX. Both sides assume a similar gigawatt build-out, so the entire revenue gap resolves into monetisation per GW. Wang's $300B on ~10 GW implies roughly $21.6B of revenue per nameplate GW per year; this model assumes about $10B, anchored to CoreWeave's disclosed economics.
A12: BRIDGE — WHAT WOULD HAVE TO CHANGE TO REACH $300B BY END-2027
A13: This model, Q4'27E annualised | B13: =B7 -> 139.6 | F13: Starting point.
A14: Required nameplate GW at THIS model's $/GW | B14: =C7*0.72/(B10) -> 21.489971 | F14: Holding monetisation at this model's rate, Wang's $300B would require this much capacity — versus the 10 GW he and SemiAnalysis actually assume. This route is not physically available on his own capacity numbers.
A15: Required $/GW at Wang's 10 GW ($B/yr) | B15: =C7*0.72/C9 -> 21.6 | F15: The other route: keep capacity as modelled and lift the rent. This is roughly 2x CoreWeave's implied ~$10.9B/GW/yr and about 3.4x SpaceX's own Q2'26A realised rate of ~$6.3B/GW/yr.
A16: Multiple of CoreWeave's implied realised rate | B16: =B15/10.9 -> 1.9816514 | F16: CoreWeave FY26 guidance: $18-19B exit ARR on ~1.7 GW of active power.
A17: Capex implied by Wang's 10 GW at this model's $/GW ($B) | B17: =(C9-1.4)*25 -> 215 | F17: Incremental GW from Q2'26A's 1.4 GW, at $25B/GW. Broadly consistent with this model's own 2027 capex, so the two sides do not differ much on spending — only on what that spending earns.
A19: WANG'S TESLA AND MERGED-ENTITY CALLS (context only — not comparable to this model)
A20: Tesla revenue, 2030 | B20: Above $1 trillion | F20: From Wang's June 2026 piece 'SpaceX and Tesla Revised Revenue and Earnings; Both Over $1T in 2030'. Driven by robotaxi, Optimus and energy storage — none of which this SpaceX model contains, so there is no line-by-line comparison to make.
A21: Merged SpaceX + Tesla revenue, 2036 | B21: $1.5-3+ quadrillion | F21: Predicated on Musk's '10x the world economy in 10 years' scenario, which Wang maps to ~27-29% global GDP CAGR. For scale, current world GDP is roughly $110 trillion, so this assumes the merged entity alone earns many times today's entire global output.
A22: Merged entity market cap, 2036 | B22: $300-1,000+ trillion | F22: Wang describes this as 'still only a few percent of the much larger global economy' under his 10x assumption. Today's entire global equity market is roughly $130 trillion.
A23: Compute scaling from 2031 | B23: 100 GW/yr -> 1 TW/yr | F23: Wang's assumed build cadence beyond this model's horizon. For reference, the Scenarios to 2030 tab shows that even 105 GW of total installed capacity equates to roughly a fifth of US average electricity demand.
A24: Assumed steady-state margins | B24: 70%+ | F24: Wang's rationale is that once capacity is built, incremental compute leasing carries very low marginal cost. This model reaches roughly 25-30% EBITDA margins, because depreciation on the build-out is charged explicitly — see the Financing & D&A tab.
A26: TRACK RECORD ON THE ONE FORECAST THAT HAS BEEN TESTED
A27: End-2026 ARR call | B27: Wang base | C27: Wang bull | D27: Company guide
A28: $B | B28: 82 | C28: 96 | D28: 100 | F28: Wang's own retrospective: 'My projection of $82B ARR for end of 2026 was low.' The single testable data point so far went AGAINST him in the conservative direction — worth weighing in both directions when judging the $300B call.
A30: READ-ACROSS
A31: The disagreement is not about gigawatts — it is about rent. Wang, SemiAnalysis and this model all work from a roughly 10 GW end-2027 base, and the implied capex is similar. The entire gap between $140B and $300B resolves into revenue per gigawatt: about $10B/GW/yr here versus roughly $21.6B implied by Wang.
A32: His case for the higher rate is specific and not unreasonable. Wang argues SpaceX takes premium spot pricing now rather than locking into the multi-year fixed contracts CoreWeave and Nebius use, and can re-let capacity or self-consume it through Grok and Cursor. If AI compute stays supply-constrained, realised rates could exceed the contracted benchmarks this model is anchored to.
A33: The case against is that no operator has yet demonstrated it. This model's $10B/GW/yr already sits at CoreWeave's disclosed level and above SpaceX's own realised Q2'26A rate of roughly $6.3B/GW/yr. Wang's figure requires roughly doubling the best rate any public comparable currently achieves, and holding it while capacity grows sevenfold.
A34: Track record cuts both ways. Wang's one testable call — end-2026 ARR — came in low, not high, and SpaceX beat it. That argues against dismissing the $300B figure as pure enthusiasm. It does not, on its own, validate a monetisation rate twice the best observed benchmark.
A35: The Tesla and merged-entity numbers are a different kind of claim. They rest on Musk's 10x-world-economy premise rather than on company-specific unit economics, and the quadrillion-scale figures exceed current global GDP by more than an order of magnitude. They are not testable against a SpaceX P&L model and are reproduced here only so the full set of Wang's published calls is visible in one place.
A36: How to use this tab: if you find Wang's monetisation argument persuasive, the lever is the 'AI infrastructure revenue per GW' row on the Assumptions tab. Raising it toward $5,400/GW/quarter reproduces his $300B end-2027 figure without touching the capacity build — and will also shorten the implied capex payback, which is the sanity check worth watching.

Sheet Case Comparison
A1: Case Comparison & Sensitivity
A2: All three cases computed live from the case library, independent of which case is currently selected. Change a case-library input on the Assumptions tab and every column here updates.
A4: Metric | B4: Case 1 Conservative | C4: Case 2 Mgmt-consistent | D4: Case 3 High-capex | F4: Benchmark / comment
A5: Currently selected on Assumptions tab | B5: =IF(Assumptions!$B$6=1,"<< ACTIVE","") -> << ACTIVE | C5: =IF(Assumptions!$B$6=2,"<< ACTIVE","") | D5: =IF(Assumptions!$B$6=3,"<< ACTIVE","")
A6: REVENUE RUN-RATE (management's exit-month x 12 basis)
A7: ARR at Dec 2026 ($mm) | B7: =('Segment Forecast'!D29*Assumptions!C12+'Segment Forecast'!D32+'Segment Forecast'!D33+'Segment Forecast'!D34+'Consolidated P&L'!F6+'Consolidated P&L'!F7)*Assumptions!$B$67*12 -> 67981.118 | C7: =('Segment Forecast'!D29*Assumptions!C15+'Segment Forecast'!D32+'Segment Forecast'!D33+'Segment Forecast'!D34+'Consolidated P&L'!F6+'Consolidated P&L'!F7)*Assumptions!$B$67*12 -> 100484.8 | D7: =('Segment Forecast'!D29*Assumptions!C18+'Segment Forecast'!D32+'Segment Forecast'!D33+'Segment Forecast'!D34+'Consolidated P&L'!F6+'Consolidated P&L'!F7)*Assumptions!$B$67*12 -> 100484.8 | F7: Management guided to $100B+ ARR by December 2026, measured as expected December revenue annualised. Case 2 is calibrated to reproduce it.
A8: ARR at Dec 2027 ($mm) | B8: =('Segment Forecast'!H29*Assumptions!G12+'Segment Forecast'!H32+'Segment Forecast'!H33+'Segment Forecast'!H34+'Consolidated P&L'!J6+'Consolidated P&L'!J7)*Assumptions!$B$67*12 -> 178721.89 | C8: =('Segment Forecast'!H29*Assumptions!G15+'Segment Forecast'!H32+'Segment Forecast'!H33+'Segment Forecast'!H34+'Consolidated P&L'!J6+'Consolidated P&L'!J7)*Assumptions!$B$67*12 -> 316205.89 | D8: =('Segment Forecast'!H29*Assumptions!G18+'Segment Forecast'!H32+'Segment Forecast'!H33+'Segment Forecast'!H34+'Consolidated P&L'!J6+'Consolidated P&L'!J7)*Assumptions!$B$67*12 -> 316205.89 | F8: SemiAnalysis and Brian Wang both independently arrive at roughly $300B by end-2027.
A9: ARR at Dec 2028 ($mm) | B9: =('Segment Forecast'!L29*Assumptions!K12+'Segment Forecast'!L32+'Segment Forecast'!L33+'Segment Forecast'!L34+'Consolidated P&L'!N6+'Consolidated P&L'!N7)*Assumptions!$B$67*12 -> 237789.43 | C9: =('Segment Forecast'!L29*Assumptions!K15+'Segment Forecast'!L32+'Segment Forecast'!L33+'Segment Forecast'!L34+'Consolidated P&L'!N6+'Consolidated P&L'!N7)*Assumptions!$B$67*12 -> 410157.43 | D9: =('Segment Forecast'!L29*Assumptions!K18+'Segment Forecast'!L32+'Segment Forecast'!L33+'Segment Forecast'!L34+'Consolidated P&L'!N6+'Consolidated P&L'!N7)*Assumptions!$B$67*12 -> 410157.43
A11: CAPITAL INTENSITY
A12: CY2027 total capex ($mm) | B12: =(MAX(0,'Segment Forecast'!E41)*Assumptions!D14+'Consolidated P&L'!G60+'Consolidated P&L'!G61)+(MAX(0,'Segment Forecast'!F41)*Assumptions!E14+'Consolidated P&L'!H60+'Consolidated P&L'!H61)+(MAX(0,'Segment Forecast'!G41)*Assumptions!F14+'Consolidated P&L'!I60+'Consolidated P&L'!I61)+(MAX(0,'Segment Forecast'!H41)*Assumptions!G14+'Consolidated P&L'!J60+'Consolidated P&L'!J61) -> 207742.25 | C12: =(MAX(0,'Segment Forecast'!E41)*Assumptions!D17+'Consolidated P&L'!G60+'Consolidated P&L'!G61)+(MAX(0,'Segment Forecast'!F41)*Assumptions!E17+'Consolidated P&L'!H60+'Consolidated P&L'!H61)+(MAX(0,'Segment Forecast'!G41)*Assumptions!F17+'Consolidated P&L'!I60+'Consolidated P&L'!I61)+(MAX(0,'Segment Forecast'!H41)*Assumptions!G17+'Consolidated P&L'!J60+'Consolidated P&L'!J61) -> 447692.25 | D12: =(MAX(0,'Segment Forecast'!E41)*Assumptions!D20+'Consolidated P&L'!G60+'Consolidated P&L'!G61)+(MAX(0,'Segment Forecast'!F41)*Assumptions!E20+'Consolidated P&L'!H60+'Consolidated P&L'!H61)+(MAX(0,'Segment Forecast'!G41)*Assumptions!F20+'Consolidated P&L'!I60+'Consolidated P&L'!I61)+(MAX(0,'Segment Forecast'!H41)*Assumptions!G20+'Consolidated P&L'!J60+'Consolidated P&L'!J61) -> 595592.25 | F12: SemiAnalysis-derived commentary implies $300-500B of capex in 2027 alone at roughly $50B per GW.
A13: CY2028 total capex ($mm) | B13: =(MAX(0,'Segment Forecast'!I41)*Assumptions!H14+'Consolidated P&L'!K60+'Consolidated P&L'!K61)+(MAX(0,'Segment Forecast'!J41)*Assumptions!I14+'Consolidated P&L'!L60+'Consolidated P&L'!L61)+(MAX(0,'Segment Forecast'!K41)*Assumptions!J14+'Consolidated P&L'!M60+'Consolidated P&L'!M61)+(MAX(0,'Segment Forecast'!L41)*Assumptions!K14+'Consolidated P&L'!N60+'Consolidated P&L'!N61) -> 122164.7 | C13: =(MAX(0,'Segment Forecast'!I41)*Assumptions!H17+'Consolidated P&L'!K60+'Consolidated P&L'!K61)+(MAX(0,'Segment Forecast'!J41)*Assumptions!I17+'Consolidated P&L'!L60+'Consolidated P&L'!L61)+(MAX(0,'Segment Forecast'!K41)*Assumptions!J17+'Consolidated P&L'!M60+'Consolidated P&L'!M61)+(MAX(0,'Segment Forecast'!L41)*Assumptions!K17+'Consolidated P&L'!N60+'Consolidated P&L'!N61) -> 325164.7 | D13: =(MAX(0,'Segment Forecast'!I41)*Assumptions!H20+'Consolidated P&L'!K60+'Consolidated P&L'!K61)+(MAX(0,'Segment Forecast'!J41)*Assumptions!I20+'Consolidated P&L'!L60+'Consolidated P&L'!L61)+(MAX(0,'Segment Forecast'!K41)*Assumptions!J20+'Consolidated P&L'!M60+'Consolidated P&L'!M61)+(MAX(0,'Segment Forecast'!L41)*Assumptions!K20+'Consolidated P&L'!N60+'Consolidated P&L'!N61) -> 447664.7
A14: Cumulative capex Q3'26E-Q4'28E ($mm) | B14: =(MAX(0,'Segment Forecast'!C41)*Assumptions!B14+'Consolidated P&L'!E60+'Consolidated P&L'!E61)+(MAX(0,'Segment Forecast'!D41)*Assumptions!C14+'Consolidated P&L'!F60+'Consolidated P&L'!F61)+(MAX(0,'Segment Forecast'!E41)*Assumptions!D14+'Consolidated P&L'!G60+'Consolidated P&L'!G61)+(MAX(0,'Segment Forecast'!F41)*Assumptions!E14+'Consolidated P&L'!H60+'Consolidated P&L'!H61)+(MAX(0,'Segment Forecast'!G41)*Assumptions!F14+'Consolidated P&L'!I60+'Consolidated P&L'!I61)+(MAX(0,'Segment Forecast'!H41)*Assumptions!G14+'Consolidated P&L'!J60+'Consolidated P&L'!J61)+(MAX(0,'Segment Forecast'!I41)*Assumptions!H14+'Consolidated P&L'!K60+'Consolidated P&L'!K61)+(MAX(0,'Segment Forecast'!J41)*Assumptions!I14+'Consolidated P&L'!L60+'Consolidated P&L'!L61)+(MAX(0,'Segment Forecast'!K41)*Assumptions!J14+'Consolidated P&L'!M60+'Consolidated P&L'!M61)+(MAX(0,'Segment Forecast'!L41)*Assumptions!K14+'Consolidated P&L'!N60+'Consolidated P&L'!N61) -> 359878.76 | C14: =(MAX(0,'Segment Forecast'!C41)*Assumptions!B17+'Consolidated P&L'!E60+'Consolidated P&L'!E61)+(MAX(0,'Segment Forecast'!D41)*Assumptions!C17+'Consolidated P&L'!F60+'Consolidated P&L'!F61)+(MAX(0,'Segment Forecast'!E41)*Assumptions!D17+'Consolidated P&L'!G60+'Consolidated P&L'!G61)+(MAX(0,'Segment Forecast'!F41)*Assumptions!E17+'Consolidated P&L'!H60+'Consolidated P&L'!H61)+(MAX(0,'Segment Forecast'!G41)*Assumptions!F17+'Consolidated P&L'!I60+'Consolidated P&L'!I61)+(MAX(0,'Segment Forecast'!H41)*Assumptions!G17+'Consolidated P&L'!J60+'Consolidated P&L'!J61)+(MAX(0,'Segment Forecast'!I41)*Assumptions!H17+'Consolidated P&L'!K60+'Consolidated P&L'!K61)+(MAX(0,'Segment Forecast'!J41)*Assumptions!I17+'Consolidated P&L'!L60+'Consolidated P&L'!L61)+(MAX(0,'Segment Forecast'!K41)*Assumptions!J17+'Consolidated P&L'!M60+'Consolidated P&L'!M61)+(MAX(0,'Segment Forecast'!L41)*Assumptions!K17+'Consolidated P&L'!N60+'Consolidated P&L'!N61) -> 817228.76 | D14: =(MAX(0,'Segment Forecast'!C41)*Assumptions!B20+'Consolidated P&L'!E60+'Consolidated P&L'!E61)+(MAX(0,'Segment Forecast'!D41)*Assumptions!C20+'Consolidated P&L'!F60+'Consolidated P&L'!F61)+(MAX(0,'Segment Forecast'!E41)*Assumptions!D20+'Consolidated P&L'!G60+'Consolidated P&L'!G61)+(MAX(0,'Segment Forecast'!F41)*Assumptions!E20+'Consolidated P&L'!H60+'Consolidated P&L'!H61)+(MAX(0,'Segment Forecast'!G41)*Assumptions!F20+'Consolidated P&L'!I60+'Consolidated P&L'!I61)+(MAX(0,'Segment Forecast'!H41)*Assumptions!G20+'Consolidated P&L'!J60+'Consolidated P&L'!J61)+(MAX(0,'Segment Forecast'!I41)*Assumptions!H20+'Consolidated P&L'!K60+'Consolidated P&L'!K61)+(MAX(0,'Segment Forecast'!J41)*Assumptions!I20+'Consolidated P&L'!L60+'Consolidated P&L'!L61)+(MAX(0,'Segment Forecast'!K41)*Assumptions!J20+'Consolidated P&L'!M60+'Consolidated P&L'!M61)+(MAX(0,'Segment Forecast'!L41)*Assumptions!K20+'Consolidated P&L'!N60+'Consolidated P&L'!N61) -> 1094428.8 | F14: For scale: SpaceX raised about $86B net at IPO and held roughly $100B of cash and securities at Jun 30, 2026.
A16: RETURNS ON NEW CAPITAL
A17: Payback on new capacity, Q4'26E (yrs, mgmt basis) | B17: =Assumptions!C14/(Assumptions!C13*4) -> 2.2727273 | C17: =Assumptions!C17/(Assumptions!C16*4) -> 1.0416667 | D17: =Assumptions!C20/(Assumptions!C19*4) -> 1.25 | F17: The CFO claimed 'less than a one-year payback' on new compute deployments. Case 2 lands at 1.04 years — close, though not strictly under one.
A18: Payback on new capacity, Q4'27E (yrs, mgmt basis) | B18: =Assumptions!G14/(Assumptions!G13*4) -> 1.9354839 | C18: =Assumptions!G17/(Assumptions!G16*4) -> 1.3181818 | D18: =Assumptions!G20/(Assumptions!G19*4) -> 1.8181818
A19: Blended revenue per GW, Q4'26E ($B/yr) | B19: =Assumptions!C12*4/1000 -> 11.6 | C19: =Assumptions!C15*4/1000 -> 26 | D19: =Assumptions!C18*4/1000 -> 26 | F19: CoreWeave's FY26 guidance implies roughly $10.9B/GW/yr on contracted, non-spot terms.
A20: Marginal contract rate, Q4'26E ($B/yr) | B20: =Assumptions!C13*4/1000 -> 13.2 | C20: =Assumptions!C16*4/1000 -> 48 | D20: =Assumptions!C19*4/1000 -> 48 | F20: SemiAnalysis puts the Google agreement at roughly $48B per GW per year; Altimeter sees 2-3x neocloud pricing.
A21: Capex per GW, Q4'26E ($B) | B21: =Assumptions!C14/1000 -> 30 | C21: =Assumptions!C17/1000 -> 50 | D21: =Assumptions!C20/1000 -> 60 | F21: Nvidia's Jensen Huang cites roughly $50B per GW today, rising toward $90B. Epoch AI models $38B; Bernstein $35B.
A24: SENSITIVITY — PAYBACK ON NEW CAPACITY (years, management basis)
A25: Capex per GW ($B) \ Marginal rate ($B/GW/yr) | B25: 12 | C25: 24 | D25: 36 | E25: 48 | F25: 60
A26: 20 | B26: =$A26/B$25 -> 1.6666667 | C26: =$A26/C$25 -> 0.83333333 | D26: =$A26/D$25 -> 0.55555556 | E26: =$A26/E$25 -> 0.41666667 | F26: =$A26/F$25 -> 0.33333333
A27: 30 | B27: =$A27/B$25 -> 2.5 | C27: =$A27/C$25 -> 1.25 | D27: =$A27/D$25 -> 0.83333333 | E27: =$A27/E$25 -> 0.625 | F27: =$A27/F$25 -> 0.5
A28: 40 | B28: =$A28/B$25 -> 3.3333333 | C28: =$A28/C$25 -> 1.6666667 | D28: =$A28/D$25 -> 1.1111111 | E28: =$A28/E$25 -> 0.83333333 | F28: =$A28/F$25 -> 0.66666667
A29: 50 | B29: =$A29/B$25 -> 4.1666667 | C29: =$A29/C$25 -> 2.0833333 | D29: =$A29/D$25 -> 1.3888889 | E29: =$A29/E$25 -> 1.0416667 | F29: =$A29/F$25 -> 0.83333333
A30: 65 | B30: =$A30/B$25 -> 5.4166667 | C30: =$A30/C$25 -> 2.7083333 | D30: =$A30/D$25 -> 1.8055556 | E30: =$A30/E$25 -> 1.3541667 | F30: =$A30/F$25 -> 1.0833333
A31: 90 | B31: =$A31/B$25 -> 7.5 | C31: =$A31/C$25 -> 3.75 | D31: =$A31/D$25 -> 2.5 | E31: =$A31/E$25 -> 1.875 | F31: =$A31/F$25 -> 1.5
A32: Values at or below 1.00 satisfy management's sub-1-year payback claim. The table shows it is achievable only where the marginal contract rate is at least roughly equal to capex per GW — which is precisely what the Google deal at ~$48B/GW against ~$50B/GW build cost implies, and precisely what Case 1's CoreWeave-anchored rates cannot deliver at any plausible build cost.
A35: MODEL LIMITATIONS & HOW TO STRESS-TEST
A36: Every editable input in this workbook is a YELLOW cell. The ones that matter most, in order of impact: the case selector and case library on the Assumptions tab (AI capex per GW, blended revenue per GW, marginal rate); the nameplate GW schedule on the same tab; and the exit-month share that converts quarterly revenue into management's ARR measure.
A37: Grok and Cursor revenue are pure assumptions with no historical anchor. SpaceX does not disclose either separately — Grok sits inside the reported 'AI solutions and infrastructure' line and Cursor was not consolidated in Q2'26. They are modelled as standalone lines only because management stated the $100B ARR trajectory is 'including contribution from Cursor'. Treat their levels as illustrative.
A38: The cash flow statement is a proxy. It excludes working capital and deferred revenue movements, both of which have historically been meaningful sources of cash for SpaceX, and it assumes no equity issuance, no debt repayment and no asset sales. The funding gap it produces indicates scale, not a financing plan.
A39: Depreciation covers new forecast-period capex only. Depreciation on assets already in service at Q2'26 stays embedded in the cost ratios inherited from reported actuals, which avoids double-counting but means the D&A line is not a complete company depreciation figure.
A40: Orbital AI compute is deliberately excluded from every calculation and held as a memo on the Segment Forecast tab. It has no revenue history, no disclosed monetisation plan, and its capex per GW is derived from SpaceX's own specifications rather than any external benchmark. A one-click toggle to fold it into the forecast was considered and rejected: it would let speculative capacity flow into revenue, valuation and payback outputs that look authoritative but rest on no observable data.
A41: The three valuation blocks disagree by an order of magnitude and none should be relied on alone. Revenue-multiple gives $207-621B, PEG gives implausible trillions, and the DCF is dominated by a manually-entered terminal assumption. SPCX actually trades near $1.43T. The model is built to interrogate operating assumptions, not to produce a price target.

Sheet Dashboard
A1: Dashboard
A2: Revenue by segment, profitability trend, and AI compute build-out — actuals + forecast through Q4 2028
A4: $mm | B4: Q2'25A | C4: Q1'26A | D4: Q2'26A | E4: Q3'26E | F4: Q4'26E | G4: Q1'27E | H4: Q2'27E | I4: Q3'27E | J4: Q4'27E | K4: Q1'28E | L4: Q2'28E | M4: Q3'28E | N4: Q4'28E
A5: Space revenue | B5: ='Consolidated P&L'!B6 -> 746 | C5: ='Consolidated P&L'!C6 -> 619 | D5: ='Consolidated P&L'!D6 -> 962 | E5: ='Consolidated P&L'!E6 -> 1058.2 | F5: ='Consolidated P&L'!F6 -> 1185.184 | G5: ='Consolidated P&L'!G6 -> 1303.7024 | H5: ='Consolidated P&L'!H6 -> 1421.0356 | I5: ='Consolidated P&L'!I6 -> 1534.7185 | ... N5: ='Consolidated P&L'!N6 -> 2132.2188
A6: Connectivity revenue | B6: ='Consolidated P&L'!B7 -> 2588 | C6: ='Consolidated P&L'!C7 -> 3257 | D6: ='Consolidated P&L'!D7 -> 4291 | E6: ='Consolidated P&L'!E7 -> 4819.2 | F6: ='Consolidated P&L'!F7 -> 5521.296 | G6: ='Consolidated P&L'!G7 -> 6147.2904 | H6: ='Consolidated P&L'!H7 -> 6817.6062 | I6: ='Consolidated P&L'!I7 -> 7426.3909 | ... N6: ='Consolidated P&L'!N7 -> 10697.319
A7: AI revenue | B7: ='Consolidated P&L'!B8 -> 737 | C7: ='Consolidated P&L'!C8 -> 818 | D7: ='Consolidated P&L'!D8 -> 2561 | E7: ='Consolidated P&L'!E8 -> 5595.66 | F7: ='Consolidated P&L'!F8 -> 8201.66 | G7: ='Consolidated P&L'!G8 -> 10843.257 | H7: ='Consolidated P&L'!H8 -> 15113.022 | I7: ='Consolidated P&L'!I8 -> 21767.932 | ... N7: ='Consolidated P&L'!N8 -> 39317.268
A8: Total revenue | B8: ='Consolidated P&L'!B9 -> 4071 | C8: ='Consolidated P&L'!C9 -> 4694 | D8: ='Consolidated P&L'!D9 -> 7814 | E8: ='Consolidated P&L'!E9 -> 11473.06 | F8: ='Consolidated P&L'!F9 -> 14908.14 | G8: ='Consolidated P&L'!G9 -> 18294.249 | H8: ='Consolidated P&L'!H9 -> 23351.663 | I8: ='Consolidated P&L'!I9 -> 30729.042 | ... N8: ='Consolidated P&L'!N9 -> 52146.805
A9: Net income (loss) | B9: ='Consolidated P&L'!B38 -> -1008 | C9: ='Consolidated P&L'!C38 -> -4276 | D9: ='Consolidated P&L'!D38 -> -541 | E9: ='Consolidated P&L'!E38 -> 39.0172 | F9: ='Consolidated P&L'!F38 -> 572.84901 | G9: ='Consolidated P&L'!G38 -> 786.65688 | H9: ='Consolidated P&L'!H38 -> 1263.4457 | I9: ='Consolidated P&L'!I38 -> 1710.476 | ... N9: ='Consolidated P&L'!N38 -> -450.71423
A10: AI nameplate compute (GW) — terrestrial | D10: 1.4 | E10: ='Segment Forecast'!C27 -> 1.8 | F10: ='Segment Forecast'!D27 -> 2.2 | G10: ='Segment Forecast'!E27 -> 3 | H10: ='Segment Forecast'!F27 -> 4.5 | I10: ='Segment Forecast'!G27 -> 7 | J10: ='Segment Forecast'!H27 -> 10 | K10: ='Segment Forecast'!I27 -> 11.5 | L10: ='Segment Forecast'!J27 -> 13 | ... N10: ='Segment Forecast'!L27 -> 15
A11: Orbital AI compute (GW) — speculative, SpaceX's own target | D11: 0 | E11: ='Segment Forecast'!C52 -> 0 | F11: ='Segment Forecast'!D52 -> 0 | G11: ='Segment Forecast'!E52 -> 0 | H11: ='Segment Forecast'!F52 -> 0.1 | I11: ='Segment Forecast'!G52 -> 0.4 | J11: ='Segment Forecast'!H52 -> 1 | K11: ='Segment Forecast'!I52 -> 2 | L11: ='Segment Forecast'!J52 -> 4 | ... N11: ='Segment Forecast'!L52 -> 10
A12: Implied AI capex payback (years) vs. <1yr guidance | D12: ='Segment Forecast'!B47 -> 4.2902299 | E12: ='Segment Forecast'!C47 -> 3.5651341 | F12: ='Segment Forecast'!D47 -> 3.4239766 | G12: ='Segment Forecast'!E47 -> 3.2777778 | H12: ='Segment Forecast'!F47 -> 3.1767677 | I12: ='Segment Forecast'!G47 -> 3.1205451 | J12: ='Segment Forecast'!H47 -> 3.1143791 | K12: ='Segment Forecast'!I47 -> 3.1077098 | ... N12: ='Segment Forecast'!L47 -> n/a
A13: SpaceX guidance: <1-year payback | D13: 1 | E13: 1 | F13: 1 | G13: 1 | H13: 1 | I13: 1 | J13: 1 | K13: 1 | L13: 1 | M13: 1 | N13: 1
A14: Implied market cap ($B, revenue-multiple) | B14: ='Consolidated P&L'!B48 -> 0 | C14: ='Consolidated P&L'!C48 -> 0 | D14: ='Consolidated P&L'!D48 -> 0 | E14: ='Consolidated P&L'!E48 -> 0 | F14: ='Consolidated P&L'!F48 -> 235.93359 | G14: ='Consolidated P&L'!G48 -> 318.44379 | H14: ='Consolidated P&L'!H48 -> 412.70792 | I14: ='Consolidated P&L'!I48 -> 529.5304 | ... N14: ='Consolidated P&L'!N48 -> 1161.3925
A15: Implied market cap ($B, PEG-based) | B15: ='Consolidated P&L'!B55 -> 0 | C15: ='Consolidated P&L'!C55 -> 0 | D15: ='Consolidated P&L'!D55 -> 0 | E15: ='Consolidated P&L'!E55 -> 0 | F15: ='Consolidated P&L'!F55 -> 0 | G15: ='Consolidated P&L'!G55 -> 0 | H15: ='Consolidated P&L'!H55 -> 0 | I15: ='Consolidated P&L'!I55 -> 0 | ... N15: ='Consolidated P&L'!N55 -> n/m
A16: Total capex ($mm) | B16: ='Consolidated P&L'!B63 -> 2825 | C16: ='Consolidated P&L'!C63 -> 10107 | D16: ='Consolidated P&L'!D63 -> 18369 | E16: ='Consolidated P&L'!E63 -> 15303.96 | F16: ='Consolidated P&L'!F63 -> 14667.841 | G16: ='Consolidated P&L'!G63 -> 25099.018 | H16: ='Consolidated P&L'!H63 -> 42514.427 | I16: ='Consolidated P&L'!I63 -> 65274.957 | ... N16: ='Consolidated P&L'!N63 -> 24206.66
A17: of which: AI capex ($mm) | B17: ='Consolidated P&L'!B62 -> 749 | C17: ='Consolidated P&L'!C62 -> 7723 | D17: ='Consolidated P&L'!D62 -> 15828 | E17: ='Consolidated P&L'!E62 -> 12800 | F17: ='Consolidated P&L'!F62 -> 12000 | G17: ='Consolidated P&L'!G62 -> 22400 | H17: ='Consolidated P&L'!H62 -> 39750 | I17: ='Consolidated P&L'!I62 -> 62500 | ... N17: ='Consolidated P&L'!N62 -> 21000
A18: of which: Space + Connectivity capex ($mm) | B18: =B16-B17 -> 2076 | C18: =C16-C17 -> 2384 | D18: =D16-D17 -> 2541 | E18: =E16-E17 -> 2503.96 | F18: =F16-F17 -> 2667.8414 | G18: =G16-G17 -> 2699.0181 | H18: =H16-H17 -> 2764.4268 | I18: =I16-I17 -> 2774.9568 | ... N18: =N16-N17 -> 3206.6599
